Workbook
Name __sqn1: '[1]compte de res charge T5'!$N$42
Name __srn1: '[1]compte de res charge T5'!$L$43
Name __tqn1: '[1]T6 compte de resultat produit'!$I$22
Name __ttn1: '[1]T6 compte de resultat produit'!$O$24
Name _azn1: #REF!
Name _bkn1: #REF!
Name _bqn1: #REF!
Name _brn1: #REF!
Name _btn1: #REF!
Name _cin1: #REF!
Name _cpn1: #REF!
Name _cum3: '[1]BALANCE N'!$J$2:$J$1001
Name _dan1: #REF!
Name _dbn1: #REF!
Name _dcn1: #REF!
Name _ddn1: #REF!
Name _dfn1: #REF!
Name _dgn1: #REF!
Name _dhn1: #REF!
Name _din1: #REF!
Name _djn1: #REF!
Name _dkn1: #REF!
Name _dln1: #REF!
Name _dmn1: #REF!
Name _dnn1: #REF!
Name _dpn1: #REF!
Name _dqn1: #REF!
Name _drn1: #REF!
Name _dsn1: #REF!
Name _dtn1: #REF!
Name _rwn1: #REF!
Name _san1: '[1]compte de res charge T5'!$N$29
Name _scn1: '[1]compte de res charge T5'!$N$30
Name _sfn1: #REF!
Name _shn1: #REF!
Name _sln1: '[1]compte de res charge T5'!$N$38
Name _son1: #REF!
Name _sqn1: #REF!
Name _srn1: #REF!
Name _ssn1: #REF!
Name _tan1: #REF!
Name _tbn1: #REF!
Name _tcn1: #REF!
Name _tdn1: #REF!
Name _tfn1: '[1]T6 compte de resultat produit'!$O$14
Name _tgn1: #REF!
Name _thn1: #REF!
Name _tkn1: #REF!
Name _tln1: #REF!
Name _tnn1: #REF!
Name _Toc12343290: 'Tendances et prévisions'!$B$7
Name _tqn1: #REF!
Name _tsn1: #REF!
Name _ttn1: #REF!
Name _txn1: #REF!
Name _uan1: '[1]T6 compte de resultat produit'!$O$28
Name _ucn1: '[1]T6 compte de resultat produit'!$O$29
Name _uen1: '[1]T6 compte de resultat produit'!$O$31
Name _ufn1: #REF!
Name _ugn1: #REF!

Sheet Bilan
C2: Désignation de l'entité: | D2: ELESYST SA | P2: Exercice clos le 31/12/ | Q2: 2019
C3: Numéro d'identification: | D3: MO1779U7P00197 | P3: Durée (en mois): | Q3: 12
C4: *Colonnes G (BRUT), I (AMORT. Et DEPREC.), T(EXERCICE au 31/12/N) et V(EXERCICE au 31/12/N-1) / Cellules K43 à 48 à renseigner manuellement
A5: BILAN AU 31 DECEMBRE N
A7: REF | C7: ACTIF | E7: Note | G7: EXERCICE au 31/12/N | M7: EXERCICE | N7: REF | P7: PASSIF | R7: Note | T7: EXERCICE | V7: EXERICE
G8: BRUT | I8: AMORT. | K8: NET | M8: AU | T8: au | V8: au
I9: et | M9: 31/12/N-1 | T9: 31/12/N | V9: 31/12/N-1
I10: DEPREC. | M10: NET | T10: NET | V10: NET
A11: AD | C11: IMMOBILISATIONS INCORPORELLES | E11: 3
A12: AE | C12: Frais de développement et de prospection | G12: 150000 | K12: =G12-I12 -> 150000 | M12: 180000 | N12: CA | P12: Capital | R12: 13 | T12: 15000000 | V12: 15000000
A13: AF | C13: Brevets, licences, logiciels, et droits similaires | G13: 500000 | K13: =G13-I13 -> 500000 | M13: 650000 | N13: CB | P13: Apporteurs capital appelé | R13: 13
A14: AG | C14: Fonds commercial et droit au bail | G14: 780000 | K14: =G14-I14 -> 780000 | M14: 1000000 | N14: CD | P14: Primes liées sans capital social | R14: 14
A15: AH | C15: Autres immobilisations corporelles | K15: =G15-I15 -> 0 | N15: CE | P15: Ecarts de réévaluation | R15: 3e
A16: AI | C16: IMMOBILISATIONS CORPORELLES | E16: 3 | K16: =G16-I16 -> 0 | N16: CF | P16: Réserves indisponibles | R16: 14 | T16: 1500000 | V16: 1500000
A17: AJ | C17: Terrains (dont le Placement en Net …………/………….) | G17: 3000000 | K17: =G17-I17 -> 3000000 | M17: 3000000 | N17: CG | P17: Réserves libres | R17: 14 | T17: 2000000 | V17: 2000000
A18: AK | C18: Bâtiments (dont le Placement en Net …………/………….) | G18: 15000000 | K18: =G18-I18 -> 15000000 | M18: 16000000 | N18: CH | P18: Report à nouveau | R18: 14 | T18: 7500000 | V18: 6000000
A19: AL | C19: Aménagements, agencements et installations | G19: 3000000 | K19: =G19-I19 -> 3000000 | M19: 3500000 | N19: CJ | P19: Résultat net de l'exercice (bénéfice + ou perte -) | T19: 6000000 | V19: 5000000
A20: AM | C20: Matériel, mobilier, et actifs biologiques | G20: 3500000 | K20: =G20-I20 -> 3500000 | M20: 4000000 | N20: CL | P20: Subventions d'investissement | R20: 15
A21: AN | C21: Matériel de transport | K21: =G21-I21 -> 0 | N21: CM | P21: Provisions règlementaires | R21: 15
A22: AP | C22: Avances et acomptes versés sur immobilisations | E22: 3 | K22: =G22-I22 -> 0 | N22: CP | P22: TOTAL CAPITAUX PROPRES ET RESSOURCES ASSIMILEES | T22: =SUM(T12:T21) -> 32000000 | V22: =SUM(V12:V21) -> 29500000
A23: AQ | C23: IMMOBILISATIONS FINANCIERES | E23: 4 | K23: =G23-I23 -> 0 | N23: DA | P23: Emprunts et dettes financières diverses | R23: 16 | T23: 8000000 | V23: 10000000
A24: AR | C24: Titres de participation | K24: =G24-I24 -> 0 | N24: DB | P24: Dettes de location acquisition | R24: 16
A25: AS | C25: Autres immobilisations financières | K25: =G25-I25 -> 0 | N25: DC | P25: Provisions pour risques et charges | R25: 16
A26: AZ | C26: TOTAL ACTIF IMMOBILISE | G26: =SUM(G12:G25) -> 25930000 | I26: =SUM(I12:I25) -> 0 | K26: =G26-I26 -> 25930000 | M26: =SUM(M12:M25) -> 28330000 | N26: DD | P26: TOTAL DETTES FINANCIERES ET RESSOURCES ASSIMILEES | T26: =SUM(T23:T25) -> 8000000 | V26: =SUM(V23:V25) -> 10000000
A27: BA | C27: ACTIF CIRCULANT HAO | E27: 5 | K27: =G27-I27 -> 0 | N27: DF | P27: TOTAL RESSOURCES STABLES | T27: =T22+T26 -> 40000000 | V27: =V22+V26 -> 39500000
A28: BB | C28: STOCKS ET ENCOURS | E28: 6 | K28: =G28-I28 -> 0 | N28: DH | P28: Dettes circulantes HAO | R28: 5 | T28: 3000000 | V28: 2500000
A29: BG | C29: CREANCES ET EMPLOIS ASSIMILES | K29: =G29-I29 -> 0 | N29: DI | P29: Clients, avances reçues | R29: 7
A30: BH | C30: Fournisseurs avances versées | E30: 17 | G30: 1500000 | K30: =G30-I30 -> 1500000 | M30: 1000000 | N30: DJ | P30: Fournisseurs d'exploitation | R30: 17 | T30: 2000000 | V30: 1500000
A31: BI | C31: Clients | E31: 7 | G31: 3000000 | K31: =G31-I31 -> 3000000 | M31: 2500000 | N31: DK | P31: Dettes fiscales et sociales | R31: 18 | T31: 1200000 | V31: 800000
A32: BJ | C32: Autres créances | E32: 8 | G32: 750000 | K32: =G32-I32 -> 750000 | M32: 500000 | N32: DM | P32: Autres dettes | R32: 19
A33: BK | C33: TOTAL ACTIF CIRCULANT | G33: =SUM(G27:G32) -> 5250000 | I33: =SUM(I27:I32) -> 0 | K33: =G33-I33 -> 5250000 | M33: =SUM(M27:M32) -> 4000000 | N33: DN | P33: Provisions pour risques à court terme | R33: 19
A34: BQ | C34: Titres de placement | E34: 9 | K34: =G34-I34 -> 0 | N34: DP | P34: TOTAL PASSIF CIRCULANT | T34: =SUM(T28:T33) -> 6200000 | V34: =SUM(V28:V33) -> 4800000
A35: BR | C35: Valeurs à encaisser | E35: 10 | K35: =G35-I35 -> 0 | N35: DQ | P35: Banques, crédits d'escompte | R35: 20 | T35: 500000 | V35: 350000
A36: BS | C36: Banques, chèques postaux, caisses et assimilés | E36: 11 | G36: 4500000 | K36: =G36-I36 -> 4500000 | M36: 3500000 | N36: DR | P36: Banques, établissements financiers et crédits de trésorerie | R36: 20
A37: BT | C37: TOTAL TRESORERIE-ACTIF | G37: =SUM(G34:G36) -> 4500000 | I37: =SUM(I34:I36) -> 0 | K37: =G37-I37 -> 4500000 | M37: =SUM(M34:M36) -> 3500000 | N37: DT | P37: TOTAL TRESORERIE-PASSIF | T37: =SUM(T35:T36) -> 500000 | V37: =SUM(V35:V36) -> 350000
A38: BU | C38: Ecart de conversion-Actif | E38: 12 | K38: =G38-I38 -> 0 | N38: DV | P38: Ecart de conversion-Passif | R38: 12
A39: BZ | C39: TOTAL GENERAL | G39: =G38+G37+G33+G26 -> 35680000 | I39: =I38+I37+I33+I26 -> 0 | K39: =G39-I39 -> 35680000 | M39: =M26+M33+M37+M38 -> 35830000 | N39: DZ | P39: TOTAL GENERAL | T39: =T27+T34+T37+T38 -> 46700000 | V39: =V27+V34+V37+V38 -> 44650000
C42: * A renseigner manuellement | P42: =K39-T39 -> -11020000
C43: *Trésorerie nette au 1er janvier N-1 (Trésorerie actif N-2 - Trésorerie passif N-2) | K43: 0
C44: *STOCKS ET ENCOURS N-2 | K44: 0
C45: *Fournisseurs avances versées N-2 | K45: 0
C46: *Clients N-2 | K46: 0
C47: *Autres créances N-2 | K47: 0
C48: *TOTAL PASSIF CIRCULANT N-2 | K48: 0
C49: *Distributions de dividendes opérées durant les exercices N et N-1 | K49: 0 | M49: 0

Sheet Cpte Résultat
C2: Désignation de l'entité: | D2: =+Bilan!D2 -> ELESYST SA | I2: Exercice clos le 31/12/ | J2: =+Bilan!Q2 -> 2019
C3: Numéro d'identification: | D3: =+Bilan!D3 -> MO1779U7P00197 | I3: Durée (en mois): | J3: =+Bilan!Q3 -> 12
C4: *Colonnes I (EXERCICE au 31/12/N) et I (EXERCICE au 31/12/N-1) à renseigner manuellement
A5: COMPTE DE RESULTAT AU 31 DECEMBRE N
A7: REF | C7: LIBELLES | G7: Note | I7: EXERCICE | K7: EXERCICE
I8: au 31/12/N | K8: au 31/12/N-1
I9: NET | K9: NET
A10: TA | C10: Ventes de marchandises | E10: A | F10: + | G10: 21 | I10: 55000000 | K10: 48000000
A11: RA | C11: Achats de marchandises | F11: - | G11: 22 | I11: 32000000 | K11: 26000000
A12: RB | C12: Variation de stocks de marchandises | F12: -/+ | G12: 6
A13: XA | C13: MARGE COMMERCIALE (Somme TA & RB) | I13: =I10-(I11+I12) -> 23000000 | K13: =K10-(K11+K12) -> 22000000
A14: TB | C14: Ventes des produits fabriqués | E14: B | F14: + | G14: 21
A15: TC | C15: Travaux, services vendus | E15: C | F15: + | G15: 21 | I15: 20000000 | K15: 16000000
A16: TD | C16: Produits accessoires | E16: D | F16: + | G16: 21 | I16: 3500000 | K16: 2800000
A17: XB | C17: CHIFFRE D'AFFAIRES (A + B + C + D) | I17: =I10+I14+I15+I16 -> 78500000 | K17: =K10+K14+K15+K16 -> 66800000
A18: TE | C18: Production stockée (ou déstockage) | F18: -/+ | G18: 6
A19: TF | C19: Produits immobilisées | G19: 21
A20: TG | C20: Subventions d'exploitation | G20: 21
A21: TH | C21: Autres produits | F21: + | G21: 21
A22: TI | C22: Transferts de charges d'exploitation | F22: + | G22: 12
A23: RC | C23: Achats de matières premières et fournitures liées | F23: - | G23: 22
A24: RD | C24: Variation de stocks de matières premières et fournitures liées | F24: -/+ | G24: 6
A25: RE | C25: Autres achats | F25: - | G25: 22 | I25: 3000000 | K25: 2500000
A26: RF | C26: Variation de stocks d'autres approvisionnements | F26: -/+ | G26: 6
A27: RG | C27: Transports | F27: - | G27: 23 | I27: 2850000 | K27: 2250000
A28: RH | C28: Services extérieurs | F28: - | G28: 24 | I28: 6000000 | K28: 5000000
A29: RI | C29: Impôts et taxes | F29: - | G29: 25 | I29: 2345000 | K29: 1950000
A30: RJ | C30: Autres charges | F30: - | G30: 26 | I30: 950000 | K30: 642000
A31: XC | C31: VALEUR AJOUTEE (XB + RA + RB) + (Somme TE à RJ) | I31: =(I17+I18+I19+I20+I21+I22)-(I11+I23+I24+I25+I26+I27+I28+I29+I30) -> 31355000 | K31: =(K17+K18+K19+K20+K21+K22)-(+K11+K23+K24+K25+K26+K27+K28+K29+K30) -> 28458000
A32: RK | C32: Charge de personnel | F32: - | G32: 27 | I32: 18255000 | K32: 17093000
A33: XD | C33: EXCEDENT BRUT D'EXPLOITATION (XC + RK) | G33: 28 | I33: =I31-I32 -> 13100000 | K33: =K31-K32 -> 11365000
A34: TJ | C34: Reprises d'amortissements, provisions et dépréciations | F34: + | G34: 28 | K34: 0
A35: RL | C35: Dotations aux amortissements, aux provisions et dépréciations | F35: - | G35: 3C & 28 | I35: 2500000 | K35: 2500000
A36: XE | C36: RESULTAT D'EXPLOITATION (XD + TJ + RL) | I36: =I33+I34-I35 -> 10600000 | K36: =K33+K34-K35 -> 8865000
A37: TK | C37: Revenus financiers et assimilés | F37: + | G37: 29
A38: TL | C38: Reprises de provisions et dépréciations financières | F38: + | G38: 28
A39: TM | C39: Transferts de charges financières | F39: + | G39: 12
A40: RM | C40: Frais financiers et charges assimilées | F40: - | G40: 29 | I40: 1200000 | K40: 965000
A41: RN | C41: Dotations aux provisions et aux dépréciations financières | F41: - | G41: 3C & 28
A42: XF | C42: RESULTAT FINANCIER (somme TK à RN) | I42: =(I37+I38+I39)-(I40+I41) -> -1200000 | K42: =(K37+K38+K39)-(K40+K41) -> -965000
A43: XG | C43: RESULTAT DES ACTIVITES ORDINAIRES (XE + XF) | I43: =I36+I42 -> 9400000 | K43: =K36+K42 -> 7900000
A44: TN | C44: Produits de cessions d'immobilisations | F44: + | G44: 3D
A45: TO | C45: Autres produits HAO | F45: + | G45: 30
A46: RO | C46: Valeurs comptables des cessions d'immobilisations | F46: - | G46: 3D
A47: RP | C47: Autres charges HAO | F47: - | G47: 30
A48: XH | C48: RESULTAT HORS ACTIVITES ORDINAIRES (Somme TN à RP) | I48: =(I44+I45)-(I46+I47) -> 0 | K48: =(K44+K45)-(K46+K47) -> 0
A49: RQ | C49: Participation des travailleurs | F49: - | G49: 30
A50: RS | C50: Impôts sur résultat | F50: - | I50: 3400000 | K50: 2900000
A51: XI | C51: RESULTAT NET (XG + XH + RQ + RS) | I51: =(I43+I48)-(I49+I50) -> 6000000 | K51: =(K43+K48)-(K49+K50) -> 5000000

Sheet Cash balance
B2: Désignation de l'entité: | C2: =+Bilan!D2 -> ELESYST SA | E2: Exercice clos le 31/12/ | F2: =+Bilan!Q2 -> 2019
B3: Numéro d'identification: | C3: =+Bilan!D3 -> MO1779U7P00197 | E3: Durée (en mois): | F3: =+Bilan!Q3 -> 12
B4: *Colonnes D (EXERCICE au 31/12/N) et F (EXERCICE au 31/12/N-1) à renseigner manuellement
B5: FLUX DE TRESORERIE DETAILLES
A7: REF | B7: LIBELLES | D7: EXERCICE N | F7: EXERCICE N-1
B9: Flux de trésorerie provenant des activités d'investissement (1) & (2)
A10: =+'Flux Trésorerie'!A20 -> FF | B10: - Décaissements liés aux acquisitions d'immobilisations incorporelles | D10: =-D11-D12-D13-D14 -> 0 | F10: =-F11-F12-F13-F14 -> 0
B11: Frais de développement et de prospection
B12: Brevets, licences, logiciels, et droits similaires
B13: Fonds commercial et droit au bail
B14: Autres immobilisations corporelles
A15: =+'Flux Trésorerie'!A21 -> FG | B15: - Décaissements liés aux acquisitions d'immobilisations corporelles | D15: =-D16-D17-D18-D19-D20-D21 -> 0 | F15: =-F16-F17-F18-F19-F20-F21 -> 0
B16: Terrains (dont le Placement en Net …………/………….)
B17: Bâtiments (dont le Placement en Net …………/………….)
B18: Aménagements, agencements et installations
B19: Matériel, mobilier, et actifs biologiques
B20: Matériel de transport
B21: Avances et acomptes versés sur immobilisations
A22: =+'Flux Trésorerie'!A22 -> FH | B22: - Décaissements liés aux acquisitions d'immobilisations financières | D22: =-D23-D24 -> 0 | F22: =-F23-F24 -> 0
B23: Titres de participation
B24: Autres immobilisations financières
A25: =+'Flux Trésorerie'!A23 -> FI | B25: + Encaissements liés aux cessions d'immobilisations incorporelles et corporelles | D25: =D26+D27+D28+D29+D30+D31+D32+D33+D34+D35 -> 0 | F25: =F26+F27+F28+F29+F30+F31+F32+F33+F34+F35 -> 0
B26: Frais de développement et de prospection
B27: Brevets, licences, logiciels, et droits similaires
B28: Fonds commercial et droit au bail
B29: Autres immobilisations corporelles
B30: Terrains (dont le Placement en Net …………/………….)
B31: Bâtiments (dont le Placement en Net …………/………….)
B32: Aménagements, agencements et installations
B33: Matériel, mobilier, et actifs biologiques
B34: Matériel de transport
B35: Avances et acomptes versés sur immobilisations
A36: =+'Flux Trésorerie'!A24 -> FJ | B36: + Encaissements liés aux cessions d'immobilisations financières | D36: =D37+D38 -> 0 | F36: =F37+F38 -> 0
B37: Titres de participation
B38: Autres immobilisations financières
A39: =+'Flux Trésorerie'!A25 -> ZC | B39: Flux de trésorerie provenant des activités d'investissement | D39: =D36+D25+D22+D15+D10 -> 0 | F39: =F36+F25+F22+F15+F10 -> 0
B41: Flux de trésorerie provenant du financement des capitaux propres
A42: =+'Flux Trésorerie'!A28 -> FK | B42: + Augmentation de capital par apports nouveaux
A43: =+'Flux Trésorerie'!A29 -> FL | B43: + Subventions d'investissement reçues
A44: =+'Flux Trésorerie'!A30 -> FM | B44: - Prélèvements sur le capital
A45: =+'Flux Trésorerie'!A31 -> FN | B45: - Dividendes versés
A46: =+'Flux Trésorerie'!A32 -> ZD | B46: Total Flux de trésorerie provenant des capitaux propres | D46: =D42+D43-D44-D45 -> 0 | F46: =F42+F43-F44-F45 -> 0
B48: Flux de trésorerie provenant du financement des capitaux étrangers
A49: =+'Flux Trésorerie'!A35 -> FO | B49: + Emprunts
A50: =+'Flux Trésorerie'!A36 -> FP | B50: + Autres dettes financières
A51: =+'Flux Trésorerie'!A37 -> FQ | B51: - Remboursements des emprunts et autres dettes financières
A52: =+'Flux Trésorerie'!A38 -> ZE | B52: Total Flux de trésorerie provenant des capitaux étrangers | D52: =D49+D50-D51 -> 0 | F52: =F49+F50-F51 -> 0
B55: (1) Déduire du montant des acquisitions de l’exercice la variation des dettes sur acquisitions d’immobilisations pour l’obtention des décaissements liés aux acquisitions d’immobilisations incorporelles, corporelles et financières.
B56: (2) Encaissements liés aux cessions d’immobilisations incorporelles, corporelles et financières = prix de cession des immobilisations – variation des créances sur cessions d’immobilisations (exercices N – N-1).
B59: Pour reconstituer le montant des acquisitions d’immobilisations corporelles de l’exercice, il faut utiliser la relation suivante par exemple :
B61: Variation des immobilisations corporelles nettes (exercices N – N-1)
B62: +Dotations aux amortissements (exercice N)
B63: +Dotations aux dépréciations (exercice N)
B64: +Valeur comptable nette des immobilisations corporelles cédées (exercice N)
B65: +Avances et acomptes sur immobilisations corporelles, payés au cours de l’exercice et non livrées
B66: - Ecart et provision spéciale de réévaluation de l’exercice, de réévaluation uniquement (exercice N)
B67: - Coûts relatifs au démantèlement, à l’enlèvement de l’immobilisation et à la remise en état du site imputés aux immobilisations de l’exercice en cours
B68: - Avances et acomptes sur immobilisations corporelles acquises au cours de l’exercice, payés au cours des exercices précédents

Sheet Flux Trésorerie
C2: Désignation de l'entité: | D2: =+Bilan!D2 -> ELESYST SA | I2: Exercice clos le 31/12/ | J2: =+Bilan!Q2 -> 2019
C3: Numéro d'identification: | D3: =+Bilan!D3 -> MO1779U7P00197 | I3: Durée (en mois): | J3: =+Bilan!Q3 -> 12
A5: TABLEAU DE FLUX DE TRESORERIE
A7: REF | C7: LIBELLES | G7: Note | I7: EXERCICE N | K7: EXERCICE N-1
A8: ZA | C8: Trésorerie nette au 1er janvier (Trésorerie actif N-1 - Trésorerie passif N-1)* | E8: A | I8: =Bilan!M36-Bilan!V37 -> 3150000 | K8: =+K47 -> 0
C10: Flux de trésorerie provenant des activités opérationnelles
A11: FA | C11: Capacité d'Autofinancement Globale (CAFG) | I11: ='INDICATEURS FIN'!D35 -> 8500000 | K11: ='INDICATEURS FIN'!F35 -> 7500000
A12: FB | C12: - Actif circulant HAO | I12: =Bilan!K27 -> 0 | K12: =Bilan!M27 -> 0
A13: FC | C13: - Variations des stocks | I13: =Bilan!K28-Bilan!M28 -> 0 | K13: =+Bilan!M28-Bilan!K44 -> 0
A14: FD | C14: - Variations des créances | I14: =(Bilan!K31-Bilan!M31)+(Bilan!K32-Bilan!M32)+(Bilan!K30-Bilan!M30) -> 1250000 | K14: =+(Bilan!M30-Bilan!K45)+(Bilan!M31-Bilan!K46)+(Bilan!M32-Bilan!K47) -> 4000000
A15: FE | C15: + Variation du passif circulant | I15: =Bilan!T34-Bilan!V34 -> 1400000 | K15: =+Bilan!V34-Bilan!K48 -> 4800000
C16: Variation du BF lié aux activités opérationnelles (FB + FC + FD + FE) | I16: =SUM(I12:I15) -> 2650000 | K16: =SUM(K12:K15) -> 8800000
A17: ZB | C17: Flux de trésorerie provenant des activités opérationnelles (somme FA à FE) | E17: B | I17: =I11-(I12+I13+I14)+I15 -> 8650000 | K17: =K11-(K12+K13+K14)+K15 -> 8300000
C19: Flux de trésorerie provenant des activités d'investissement
A20: FF | C20: - Décaissements liés aux acquisitions d'immobilisations incorporelles | I20: ='Cash balance'!D10 -> 0 | K20: ='Cash balance'!F10 -> 0
A21: FG | C21: - Décaissements liés aux acquisitions d'immobilisations corporelles | I21: ='Cash balance'!D15 -> 0 | K21: ='Cash balance'!F15 -> 0
A22: FH | C22: - Décaissements liés aux acquisitions d'immobilisations financières | I22: ='Cash balance'!D22 -> 0 | K22: ='Cash balance'!F22 -> 0
A23: FI | C23: + Encaissements liés aux cessions d'immobilisations incorporelles et corporelles | I23: ='Cash balance'!D25 -> 0 | K23: ='Cash balance'!F25 -> 0
A24: FJ | C24: + Encaissements liés aux cessions d'immobilisations financières | I24: ='Cash balance'!D36 -> 0 | K24: ='Cash balance'!F36 -> 0
A25: ZC | C25: Flux de trésorerie provenant des activités d'investissement (somme FF à FJ) | E25: C | I25: =-(I20+I21+I22)+(I23+I24) -> 0 | K25: =-(K20+K21+K22)+(K23+K24) -> 0
C27: Flux de trésorerie provenant du financement des capitaux propres
A28: FK | C28: + Augmentation de capital par apports nouveaux | I28: ='Cash balance'!D42 -> 0 | K28: ='Cash balance'!F42 -> 0
A29: FL | C29: + Subventions d'investissement reçues | I29: ='Cash balance'!D43 -> 0 | K29: ='Cash balance'!F43 -> 0
A30: FM | C30: - Prélèvements sur le capital | I30: ='Cash balance'!D44 -> 0 | K30: ='Cash balance'!F44 -> 0
A31: FN | C31: - Dividendes versés | I31: ='Cash balance'!D45 -> 0 | K31: ='Cash balance'!F45 -> 0
A32: ZD | C32: Flux de trésorerie provenant des capitaux propres (somme FK à FN) | E32: D | I32: =(I28+I29)-(I30+I31) -> 0 | K32: =(K28+K29)-(K30+K31) -> 0
C34: Flux de trésorerie provenant du financement des capitaux étrangers
A35: FO | C35: + Emprunts | I35: ='Cash balance'!D49 -> 0 | K35: ='Cash balance'!F49 -> 0
A36: FP | C36: + Autres dettes financières | I36: ='Cash balance'!D50 -> 0 | K36: ='Cash balance'!F50 -> 0
A37: FQ | C37: - Remboursements des emprunts et autres dettes financières | I37: ='Cash balance'!D51 -> 0 | K37: ='Cash balance'!F51 -> 0
A38: ZE | C38: Flux de trésorerie provenant des capitaux étrangers (somme FO à FQ) | E38: E | I38: =SUM(I35:I37) -> 0 | K38: =SUM(K35:K37) -> 0
A39: ZF | C39: Flux de trésorerie provenant des activités de financement (D + E) | E39: F | I39: =I32+I38 -> 0 | K39: =K32+K38 -> 0
A41: ZG | C41: VARIATION DE LA TRESORERIE NETTE DE LA PERIODE (B + C + F) | E41: G | I41: =I17+I25+I39 -> 8650000 | K41: =K17+K25+K39 -> 8300000
A42: ZH | C42: Trésorerie nette au 31 décembre (G + A) (1) | E42: H | I42: =I41+I8 -> 11800000 | K42: =K41+K8 -> 8300000
A44: (1) Contrôle: Trésorerie actif N - Trésorerie passif N = | I44: =Bilan!K37-Bilan!T37 -> 4000000 | K44: =Bilan!M37-Bilan!V37 -> 3150000
I45: =I42-I44 -> 7800000 | K45: =K42-K44 -> 5150000

Sheet GRILLE NOTATION
A1: Désignation de l'entité: | B1: =+Bilan!D2 -> ELESYST SA | G1: Exercice clos le 31/12/ | H1: =+Bilan!Q2 -> 2019
A2: Numéro d'identification: | B2: =+Bilan!D3 -> MO1779U7P00197 | G2: Durée (en mois): | H2: =+Bilan!Q3 -> 12
A4: CRITERES PRINCIPAUX | B4: PONDERATION | C4: N° SOUS-CRITERES | D4: Taux Pondération | F4: SOUS-CRITERES | G4: VALEUR PAR SOUS-CRITERE | H4: NOTE PAR SOUS-CRITERE | I4: NOTE PONDEREE | J4: NOTE PONDEREE CRITERE
A5: ACTIVITE | B5: 0.1 | C5: 1 | D5: 0.015 | E5: positionnement concurentiel sur le marché | G5: Plutôt Moyen | H5: =IF(G5="","",VLOOKUP(G5,'tableaux annexes'!C:D,2,0)) -> 6 | I5: =+D5*H5 -> 0.09 | J5: ACTIVITE
C6: 2 | D6: 0.01 | E6: Tendance structurelle du marché | G6: très bonne A | H6: =IF(G6="","",VLOOKUP(G6,'tableaux annexes'!K:M,2,0)) -> 1 | I6: =+D6*H6 -> 0.01
C7: 3 | D7: 0.01 | E7: Marchés cycliques ou à prix volatils | G7: peu | H7: =IF(G7="","",VLOOKUP(G7,'tableaux annexes'!G:H,2,0)) -> 3 | I7: =+D7*H7 -> 0.03
C8: 4 | D8: 0.02 | E8: Portefeuille produit | G8: plutot bien positionné | H8: =IF(G8="","",VLOOKUP(G8,'tableaux annexes'!O:P,2,0)) -> 3 | I8: =+D8*H8 -> 0.06
C9: 5 | D9: 0.02 | E9: Pression liée à la clientèle | G9: très modérée | H9: =IF(G9="","",VLOOKUP(G9,'tableaux annexes'!S:T,2,0)) -> 1 | I9: =+D9*H9 -> 0.02
C10: 6 | D10: 0.015 | E10: Barrière à l'entrée | G10: plutôt faibles | H10: =IF(G10="","",VLOOKUP(G10,'tableaux annexes'!W:X,2,0)) -> 5 | I10: =+D10*H10 -> 0.075
C11: 7 | D11: 0.01 | E11: Visibilité du secteur | G11: très bonne B | H11: =IF(G11="","",VLOOKUP(G11,'tableaux annexes'!AA:AB,2,0)) -> 2 | I11: =+D11*H11 -> 0.02 | J11: =SUM(I5:I11) -> 0.305
A13: GESTION ET STRATEGIE | B13: 0.2 | C13: 8 | D13: 0.04 | E13: Qualité du profil du drigeant | G13: très mauvaise A | H13: =IF(G13="","",VLOOKUP(G13,'tableaux annexes'!AE:AF,2,0)) -> 9 | I13: =+D13*H13 -> 0.36 | J13: GESTION & STRATEGIE
C14: 9 | D14: 0.01 | E14: Qualité de l'organisation | G14: bonne | H14: =IF(G14="","",VLOOKUP(G14,'tableaux annexes'!AM:AN,2,0)) -> 3 | I14: =+D14*H14 -> 0.03
C15: 10 | D15: 0.01 | E15: Qualité du système de contrôle interne | G15: excellente | H15: =IF(G15="","",VLOOKUP(G15,'tableaux annexes'!AM:AN,2,0)) -> 1 | I15: =+D15*H15 -> 0.01
C16: 11 | D16: 0.01 | E16: Qualité de la Stratégie commerciale et marketing | G16: très bonne | H16: =IF(G16="","",VLOOKUP(G16,'tableaux annexes'!AM:AN,2,0)) -> 2 | I16: =+D16*H16 -> 0.02
C17: 12 | D17: 0.02 | E17: Qualité des Moyens humains et techniques | G17: assez bonne | H17: =IF(G17="","",VLOOKUP(G17,'tableaux annexes'!AM:AN,2,0)) -> 4 | I17: =+D17*H17 -> 0.08
C18: 13 | D18: 0.03 | E18: Adéquation des investissements / Impact sur l'emploi | G18: insuffisants A | H18: =IF(G18="","",VLOOKUP(G18,'tableaux annexes'!AQ:AR,2,0)) -> 7 | I18: =+D18*H18 -> 0.21
C19: 14 | D19: 0.03 | E19: Maîtrise des coûts de productivité / Impact sur la création des richesses | G19: limité | H19: =IF(G19="","",VLOOKUP(G19,'tableaux annexes'!AU:AV,2,0)) -> 8 | I19: =+D19*H19 -> 0.24
C20: 15 | D20: 0.03 | E20: Cohérence des options stratégiques / Impact sur l'environnement | G20: très fiables dans l'ensemble | H20: =IF(G20="","",VLOOKUP(G20,'tableaux annexes'!AY:AZ,2,0)) -> 1 | I20: =+D20*H20 -> 0.03
C21: 16 | D21: 0.01 | E21: Qualité des relations sociales | G21: très bonne | H21: =IF(G21="","",VLOOKUP(G21,'tableaux annexes'!BC:BD,2,0)) -> 2 | I21: =+D21*H21 -> 0.02
C22: 17 | D22: 0.01 | E22: Succession des Dirigeants | G22: Garantie par le cadre juridique et fonctionnel | H22: =IF(G22="","",VLOOKUP(G22,'tableaux annexes'!BG:BH,2,0)) -> 3 | I22: =+D22*H22 -> 0.03 | J22: =SUM(I13:I22) -> 1.03
A24: FINANCES | B24: PONDERATION | E24: SOUS-CRITERES | G24: VALEURS SOUS-CRITERES | H24: NOTE PAR SOUS-CRITERES | I24: NOTE PONDEREE | J24: NOTE PONDEREE CRITERE
A25: STRUCTURE FINANCIERE | B25: 0.45 | C25: 18 | D25: 0.03 | F25: Dynamique de l'Equilibre Financier (FR/BFR) | G25: ='INDICATEURS FIN'!D78 -> -14.810526 | H25: =IF(G25<0.2,10,IF(G25<=0.5,9,IF(G25<=0.8,8,IF(G25<=1,7,IF(G25<=1.2,6,IF(G25<=1.4,5,IF(G25<=1.6,4,IF(G25<=1.8,3,IF(G25<=2,2,1))))))))) -> 10 | I25: =H25*D25 -> 0.3 | J25: FINANCIER
C26: 19 | D26: 0.03 | F26: Ratio d'endettement global ((Actifs - Capitaux propres)/ Actifs) <1 | G26: ='INDICATEURS FIN'!D79 -> 0.10313901 | H26: =IF(G26<0.1,1,IF(G26<=0.2,2,IF(G26<0.4,3,IF(G26<0.45,4,IF(G26<0.49,5,IF(G26<0.6,6,IF(G26<0.7,7,IF(G26<0.8,8,IF(G26<1,9,10))))))))) -> 2 | I26: =H26*D26 -> 0.06
A27: LIQUIDITE ET SOLVABILITE | C27: 20 | D27: 0.04 | F27: Capacité de Remboursement (DLMT/CAFG) | G27: ='INDICATEURS FIN'!D80 -> 0.94117647 | H27: =IF(G27<1,1,IF(G27<1.5,2,IF(G27<2,3,IF(G27<3,4,IF(G27<3.4,5,IF(G27<3.8,6,IF(G27<4,7,IF(G27<4.4,8,IF(G27<5,9,10))))))))) -> 1 | I27: =H27*D27 -> 0.04
C28: 21 | D28: 0.04 | F28: Couverture des frais financiers (FTAO/FF) | G28: ='INDICATEURS FIN'!D81 -> 7.2083333 | H28: =IF(G28>6,1,IF(G28>5,2,IF(G28>4,3,IF(G28>3,4,IF(G28=3,5,IF(G28<3,6,IF(G28<2,7,IF(G28<1.5,8,IF(G28<1,9,10))))))))) -> 1 | I28: =H28*D28 -> 0.04
C29: 22 | D29: 0.04 | F29: Solvabilité globale Risque liquidatif (Ressources Propres /Total Bilan) | G29: ='INDICATEURS FIN'!D82 -> 0.68522484 | H29: =IF(G29<3%,10,IF(G29<5,9,IF(G29<10%,8,IF(G29<15%,7,IF(G29<20%,6,IF(G29<25%,5,IF(G29=25%,4,IF(G29>25%,3,IF(G29>30%,2,IF(G29>35%,1)))))))))) -> 9 | I29: =H29*D29 -> 0.36
C30: 23 | D30: 0.04 | F30: Liquidité générale (Ratio de FR= Actifs circulants/ Passifs circulants)>1 | G30: ='INDICATEURS FIN'!D83 -> 0.84677419 | H30: =IF(G30<0.2,10,IF(G30<=0.5,9,IF(G30<=0.8,8,IF(G30<=1,7,IF(G30<=1.2,6,IF(G30<=1.4,5,IF(G30<=1.6,4,IF(G30<=1.8,3,IF(G30<=2,2,1))))))))) -> 7 | I30: =H30*D30 -> 0.28
A31: PERFORMANCE DE L'ACTIVITE ET RENTABILITE | C31: 24 | D31: 0.05 | F31: Rentabilité d'exploitation par rapport au CA (EBE/ CA)>30% | G31: ='INDICATEURS FIN'!D84 -> 5.9923664 | H31: =IF(G31<10%,10,IF(G31<15%,9,IF(G31<25%,8,IF(G31<30%,7,IF(G31=30%,6,IF(G31>30%,5,IF(G31>35%,4,IF(G31>40%,3,IF(G31>45%,2,IF(G31>50%,1)))))))))) -> 5 | I31: =H31*D31 -> 0.25
C32: 25 | D32: 0.04 | F32: Rentabilité économique ( REX/ACTIF)>10% | G32: ='INDICATEURS FIN'!D85 -> 0.2970852 | H32: =IF(G32<1%,10,IF(G32<3%,9,IF(G32<5%,8,IF(G32<7.5%,7,IF(G32<10%,6,IF(G32=10%,5,IF(G32>12.5%,4,IF(G32>15%,3,IF(G32>17.5%,2,IF(G32>20%,1)))))))))) -> 4 | I32: =H32*D32 -> 0.16
C33: 26 | D33: 0.04 | F33: Rentabilité Financière (RN/Capitaux propres)>10% | G33: ='INDICATEURS FIN'!D86 -> 5.3333333 | H33: =IF(G33<1%,10,IF(G33<3%,9,IF(G33<5%,8,IF(G33<7.5%,7,IF(G33<10%,6,IF(G33=10%,5,IF(G33>12.5%,4,IF(G33>15%,3,IF(G33>17.5%,2,IF(G33>20%,1)))))))))) -> 4 | I33: =H33*D33 -> 0.16
C34: 27 | D34: 0.04 | F34: Capacité d'endettement (Ressources Propres/Dettes structurelles)>1 | G34: ='INDICATEURS FIN'!D87 -> 4 | H34: =IF(G34<0.2,10,IF(G34<0.5,9,IF(G34<0.8,8,IF(G34<1,7,IF(G34=1,6,IF(G34>1.2,5,IF(G34>1.4,4,IF(G34>1.6,3,IF(G34>1.8,2,IF(G34>2,1)))))))))) -> 5 | I34: =H34*D34 -> 0.2
A35: OUTILS D'AJUSTEMENT | C35: 28 | D35: 0.02 | F35: Délai Client ( (créances client /CA)*365) | G35: ='INDICATEURS FIN'!D88 -> 13.949045 | H35: =IF(G35<10,1,IF(G35<20,2,IF(G35<30,3,IF(G35<40,4,IF(G35<50,5,IF(G35<60,6,IF(G35<70,7,IF(G35<80,8,IF(G35<90,9,10))))))))) -> 2 | I35: =H35*D35 -> 0.04
C36: 29 | D36: 0.02 | F36: Délai Fournisseur ( (dettes fournisseurs /Achats à crédit)*365) | G36: ='INDICATEURS FIN'!D89 -> 243.33333 | H36: =IF(G36<10,10,IF(G36<=20,9,IF(G36<=30,8,IF(G36<=40,7,IF(G36<=50,6,IF(G36<=60,5,IF(G36<=70,4,IF(G36<=80,3,IF(G36<=90,2,1))))))))) -> 1 | I36: =H36*D36 -> 0.02
C37: 30 | D37: 0.02 | F37: Délai d'Ecoulement des stocks ( (stock moyen/Coûts des produits vendus)*365 ) | G37: ='INDICATEURS FIN'!D90 -> 0 | H37: =IF(G37<20,1,IF(G37<40,2,IF(G37<60,3,IF(G37<80,4,IF(G37<100,5,IF(G37<120,6,IF(G37<140,7,IF(G37<160,8,IF(G37<180,9,10))))))))) -> 1 | I37: =H37*D37 -> 0.02 | J37: =SUM(I25:I37) -> 1.93
A39: QUALITE DE L'INFORMATION FINANCIERE ET GARANTIES | B39: 0.25 | C39: 31 | D39: 0.05 | E39: Fiabilité des prévisions / Evolution des produits & charges | G39: fiable | H39: =IF(G39="","",VLOOKUP(G39,'tableaux annexes'!BK:BL,2,0)) -> 2 | I39: =+D39*H39 -> 0.1 | J39: QUALITE INFORMATIONS
C40: 32 | D40: 0.05 | E40: Représentation fidèle réalité comptable et financière/ Transparence des transactions | G40: excellente | H40: =IF(G40="","",VLOOKUP(G40,'tableaux annexes'!BO:BP,2,0)) -> 1 | I40: =+D40*H40 -> 0.05
C41: 33 | D41: 0.05 | E41: Implication du dirigeant / Surface financière des promoteurs | G41: très facile en permanence | H41: =IF(G41="","",VLOOKUP(G41,'tableaux annexes'!BS:BT,2,0)) -> 1 | I41: =+D41*H41 -> 0.05
C42: 34 | D42: 0.1 | E42: Qualité des garanties & Actifs cessibles | G42: oui, rapidement et importants | H42: =IF(G42="","",VLOOKUP(G42,'tableaux annexes'!BW:BX,2,0)) -> 1 | I42: =+D42*H42 -> 0.1 | J42: =SUM(I39:I42) -> 0.3
G43: NOTE PONDEREE FINALE / CRITERE | I43: NOTATION PME
G44: =+J42+J37+J22+J11 -> 3.565 | I44: =IF(G44<1.5,"SME1",IF(G44<2.75,"SME2",IF(G44<3.5,"SME3",IF(G44<3.75,"SME4",IF(G44<4,"SME4",IF(G44<5,"SME5",IF(G44<6,"SME6",IF(G44<7,"SME7",IF(G44<8,"SME7-",IF(G44<9,"SME8",IF(G44<9.7,"SME8-"))))))))))) -> SME4

Sheet INDICATEURS FIN
A2: Désignation de l'entité: | B2: =+Bilan!D2 -> ELESYST SA | F2: Exercice clos le 31/12/ | G2: =+Bilan!Q2 -> 2019
A3: Numéro d'identification: | B3: =+Bilan!D3 -> MO1779U7P00197 | F3: Durée (en mois): | G3: =+Bilan!Q3 -> 12
A6: FICHE DE SYNTHESE DES PRINCIPAUX INDICATEURS FINANCIERS
A8: EN MILLIONS DE FRANCS | D8: Année N | F8: Année N-1 | H8: Variation en %
A10: ANALYSE DE L'ACTIVITE
A11: SOLDES INTERMEDIAIRES DE GESTION | H11: =(D11-F11)/F11 -> #DIV/0!
A12: CHIFFRE D'AFFAIRES | D12: ='Cpte Résultat'!I17 -> 78500000 | F12: ='Cpte Résultat'!K17 -> 66800000 | H12: =(D12-F12)/F12 -> 0.1751497
A13: MARGE COMMERCIALE | D13: ='Cpte Résultat'!I13 -> 23000000 | F13: ='Cpte Résultat'!K13 -> 22000000 | H13: =(D13-F13)/F13 -> 0.045454545
A14: VALEUR AJOUTEE | D14: ='Cpte Résultat'!I31 -> 31355000 | F14: ='Cpte Résultat'!K31 -> 28458000 | H14: =(D14-F14)/F14 -> 0.10179914
A15: EXCEDENT BRUT D'EXPLOITATION (EBE) | D15: ='Cpte Résultat'!I33 -> 13100000 | F15: ='Cpte Résultat'!K33 -> 11365000 | H15: =(D15-F15)/F15 -> 0.15266168
A16: RESULTAT D'EXPLOITATION | D16: ='Cpte Résultat'!I36 -> 10600000 | F16: ='Cpte Résultat'!K36 -> 8865000 | H16: =(D16-F16)/F16 -> 0.19571348
A17: RESULTAT FINANCIER | D17: ='Cpte Résultat'!I42 -> -1200000 | F17: ='Cpte Résultat'!K42 -> -965000 | H17: =(D17-F17)/F17 -> 0.24352332
A18: RESULTAT DES ACTIVITES ORDINAIRES | D18: ='Cpte Résultat'!I43 -> 9400000 | F18: ='Cpte Résultat'!K43 -> 7900000 | H18: =(D18-F18)/F18 -> 0.18987342
A19: RESULTAT HORS ACTIVITES ORDINAIRES | D19: ='Cpte Résultat'!I48 -> 0 | F19: ='Cpte Résultat'!K48 -> 0 | H19: =(D19-F19)/F19 -> #DIV/0!
A20: RESULTAT NET | D20: ='Cpte Résultat'!I51 -> 6000000 | F20: ='Cpte Résultat'!K51 -> 5000000 | H20: =(D20-F20)/F20 -> 0.2
A21: DETERMINATION DE LA CAPACITE D'AUTOFINANCEMENT | H21: =(D21-F21)/F21 -> #DIV/0!
A22: EBE | D22: =D15 -> 13100000 | F22: =F15 -> 11365000 | H22: =(D22-F22)/F22 -> 0.15266168
A23: + Valeurs comptables des cessions courantes d’immobilisation (compte 654) | D23: ='Cpte Résultat'!I46 -> 0 | F23: ='Cpte Résultat'!K46 -> 0 | H23: =(D23-F23)/F23 -> #DIV/0!
A24: - Produits des cessions courantes d’immobilisation (compte 754) | D24: ='Cpte Résultat'!I44 -> 0 | F24: ='Cpte Résultat'!K44 -> 0 | H24: =(D24-F24)/F24 -> #DIV/0!
A25: = CAPACITE D'AUTOFINANCEMENT D'EXPLOITATION | D25: =D22+D23-D24 -> 13100000 | F25: =F22+F23-F24 -> 11365000 | H25: =(D25-F25)/F25 -> 0.15266168
A26: + Revenus financiers | D26: ='Cpte Résultat'!I37 -> 0 | F26: ='Cpte Résultat'!K37 -> 0 | H26: =(D26-F26)/F26 -> #DIV/0!
A27: + Gains de change | H27: =(D27-F27)/F27 -> #DIV/0!
A28: + Transferts de charges financières | D28: ='Cpte Résultat'!I39 -> 0 | F28: ='Cpte Résultat'!K39 -> 0 | H28: =(D28-F28)/F28 -> #DIV/0!
A29: + Produits HAO | D29: ='Cpte Résultat'!I45 -> 0 | F29: ='Cpte Résultat'!K45 -> 0 | H29: =(D29-F29)/F29 -> #DIV/0!
A30: + Transferts de charges HAO | H30: =(D30-F30)/F30 -> #DIV/0!
A31: - Frais financiers | D31: ='Cpte Résultat'!I40 -> 1200000 | F31: ='Cpte Résultat'!K40 -> 965000 | H31: =(D31-F31)/F31 -> 0.24352332
A32: - Pertes de change | H32: =(D32-F32)/F32 -> #DIV/0!
A33: - Participation | D33: ='Cpte Résultat'!I49 -> 0 | F33: ='Cpte Résultat'!K49 -> 0 | H33: =(D33-F33)/F33 -> #DIV/0!
A34: - Impôts sur les résultats | D34: ='Cpte Résultat'!I50 -> 3400000 | F34: ='Cpte Résultat'!K50 -> 2900000 | H34: =(D34-F34)/F34 -> 0.17241379
A35: = CAPACITE D'AUTOFINANCEMENT GLOBALE (C.A.F.G.) | D35: =D25+(D26+D27+D28+D29+D30)-(D31+D32+D33+D34) -> 8500000 | F35: =F25+(F26+F27+F28+F29+F30)-(F31+F32+F33+F34) -> 7500000 | H35: =(D35-F35)/F35 -> 0.13333333
A36: - Distributions de dividendes opérées durant l'exercice | D36: =Bilan!K49 -> 0 | F36: =Bilan!M49 -> 0 | H36: =(D36-F36)/F36 -> #DIV/0!
A37: = AUTOFINANCEMENT | D37: =D35-D36 -> 8500000 | F37: =F35-F36 -> 7500000 | H37: =(D37-F37)/F37 -> 0.13333333
A39: ANALYSE DE LA RENTABILITE
A40: Rentabilité économique = Résultat d’exploitation (a) /Capitaux propres + dettes financières | D40: =D16/(Bilan!T12+Bilan!T23) -> 0.46086957 | F40: =F16/(Bilan!V12+Bilan!V23) -> 0.3546 | H40: =(D40-F40)/F40 -> 0.29968857
A41: Rentabilité financière = Résultat net/Capitaux propres | D41: =D20/Bilan!T12 -> 0.4 | F41: =F20/Bilan!V12 -> 0.33333333 | H41: =(D41-F41)/F41 -> 0.2
A43: ANALYSE DE LA STRUCTURE FINANCIERE
A44: Capitaux propres et ressources assimilées | D44: =Bilan!T22 -> 32000000 | F44: =Bilan!V22 -> 29500000 | H44: =(D44-F44)/F44 -> 0.084745763
A45: + Dettes financières* et autres ressources assimilées (b) | D45: =Bilan!T26 -> 8000000 | F45: =Bilan!V26 -> 10000000 | H45: =(D45-F45)/F45 -> -0.2
A46: = ressources stables | D46: =D44+D45 -> 40000000 | F46: =F44+F45 -> 39500000 | H46: =(D46-F46)/F46 -> 0.012658228
A47: - Actif immobilisé (b) | D47: =Bilan!K26 -> 25930000 | F47: =Bilan!M26 -> 28330000 | H47: =(D47-F47)/F47 -> -0.084715849
A48: = FONDS DE ROULEMENT (1) | D48: =D46-D47 -> 14070000 | F48: =F46-F47 -> 11170000 | H48: =(D48-F48)/F48 -> 0.25962399
A49: Actif circulant d'exploitation (b) | D49: =Bilan!K33-Bilan!K27 -> 5250000 | F49: =Bilan!M33-Bilan!M27 -> 4000000 | H49: =(D49-F49)/F49 -> 0.3125
A50: - Passif circulant d'exploitation (b) | D50: =Bilan!T34-Bilan!T28 -> 3200000 | F50: =Bilan!V34-Bilan!V28 -> 2300000 | H50: =(D50-F50)/F50 -> 0.39130435
A51: = BESOIN DE FINANCEMENT D'EXPLOITATION (2) | D51: =D49-D50 -> 2050000 | F51: =F49-F50 -> 1700000 | H51: =(D51-F51)/F51 -> 0.20588235
A52: Actif circulant HAO (b) | D52: =Bilan!K27 -> 0 | F52: =Bilan!M27 -> 0 | H52: =(D52-F52)/F52 -> #DIV/0!
A53: - Passif circulant HAO (b) | D53: =Bilan!T28 -> 3000000 | F53: =Bilan!V28 -> 2500000 | H53: =(D53-F53)/F53 -> 0.2
A54: = BESOIN DE FINANCEMENT HAO (3) | D54: =D52-D53 -> -3000000 | F54: =F52-F53 -> -2500000 | H54: =(D54-F54)/F54 -> 0.2
A55: BESOIN DE FINANCEMENT GLOBAL (4) = (2) + (3) | D55: =D51+D54 -> -950000 | F55: =F51+F54 -> -800000 | H55: =(D55-F55)/F55 -> 0.1875
A56: TRESORERIE NETTE (5) = (1) - (4) | D56: =D48-D55 -> 15020000 | F56: =F48-F55 -> 11970000 | H56: =(D56-F56)/F56 -> 0.25480368
A57: CONTRÔLE : TRESOR. NETTE = (TRESOR. - ACTIF) - (TRESOR. - PASSIF) | D57: =Bilan!K37-Bilan!T37 -> 4000000 | F57: =Bilan!M37-Bilan!V37 -> 3150000
A59: ANALYSE DE LA VARIATION DE LA TRESORERIE
A60: Flux de trésorerie des activités opérationnelles | D60: ='Flux Trésorerie'!I17 -> 8650000 | F60: ='Flux Trésorerie'!K17 -> 8300000 | H60: =(D60-F60)/F60 -> 0.042168675
A61: - Flux de trésorerie des activités d'investissement | D61: ='Flux Trésorerie'!I25 -> 0 | F61: ='Flux Trésorerie'!K25 -> 0 | H61: =(D61-F61)/F61 -> #DIV/0!
A62: + Flux de trésorerie des activités de FINANCEMENT | D62: ='Flux Trésorerie'!I39 -> 0 | F62: ='Flux Trésorerie'!K39 -> 0 | H62: =(D62-F62)/F62 -> #DIV/0!
A63: = VARIATION DE LA TRESORERIE NETTE DE LA PERIODE | D63: =D60-D61+D62 -> 8650000 | F63: =F60-F61+F62 -> 8300000 | H63: =(D63-F63)/F63 -> 0.042168675
A65: ANALYSE DE LA VAR. DE L’ENDETTEMENT FINANCIER NET
A66: Endettement financier brut (Dettes financières* + Trésorerie – passif) | D66: =Bilan!T23+Bilan!T24+Bilan!T37 -> 8500000 | F66: =Bilan!V23+Bilan!V24+Bilan!V37 -> 10350000 | H66: =(D66-F66)/F66 -> -0.17874396
A67: - Trésorerie - actif | D67: =Bilan!K37 -> 4500000 | F67: =Bilan!M37 -> 3500000 | H67: =(D67-F67)/F67 -> 0.28571429
A68: = ENDETTEMENT FINANCIER NET | D68: =D66-D67 -> 4000000 | F68: =F66-F67 -> 6850000 | H68: =(D68-F68)/F68 -> -0.41605839
A70: (a) Résultat d’exploitation après impôt théorique sur le bénéfice.
A71: (b) Les écarts de conversion doivent être éliminés afin de ramener les créances et les dettes concernées à leur valeur initiale.
A72: Dettes financières* = emprunts et dettes financières diverses + dettes de location acquisition.
A75: RATIOS USUELS
A76: Stock moyen** | D76: =(Bilan!M28+Bilan!K28)/2 -> 0 | F76: =(Bilan!K44+Bilan!M28)/2 -> 0 | H76: =(D76-F76)/F76 -> #DIV/0!
A77: Coût des produits vendus | D77: ='Cpte Résultat'!I22+'Cpte Résultat'!I23+'Cpte Résultat'!I24+'Cpte Résultat'!I26+'Cpte Résultat'!I27+'Cpte Résultat'!I28+'Cpte Résultat'!I29+'Cpte Résultat'!I30+'Cpte Résultat'!I32+'Cpte Résultat'!I35 -> 32900000 | F77: ='Cpte Résultat'!K22+'Cpte Résultat'!K23+'Cpte Résultat'!K24+'Cpte Résultat'!K25+'Cpte Résultat'!K26+'Cpte Résultat'!K27+'Cpte Résultat'!K28+'Cpte Résultat'!K29+'Cpte Résultat'!K30+'Cpte Résultat'!K32+'Cpte Résultat'!K35 -> 31935000 | H77: =(D77-F77)/F77 -> 0.03021763
A78: Dynamique de l'Equilibre Financier (FR/BFR) | D78: =+D48/D55 -> -14.810526 | F78: =F48/F55 -> -13.9625 | H78: =(D78-F78)/F78 -> 0.060735994
A79: Ratio d'endettement global ((Actif-Capitaux propres)/Actif) | D79: =(Bilan!K39-Bilan!T22)/Bilan!K39 -> 0.10313901 | F79: =(Bilan!M39-Bilan!V22)/Bilan!M39 -> 0.1766676 | H79: =(D79-F79)/F79 -> -0.41619734
A80: Capacité de Remboursement (DLMT/CAFG) | D80: =(Bilan!T23+Bilan!T24)/'INDICATEURS FIN'!D35 -> 0.94117647 | F80: =(Bilan!V23+Bilan!V24)/'INDICATEURS FIN'!F35 -> 1.3333333 | H80: =(D80-F80)/F80 -> -0.29411765
A81: Couverture des frais financiers (FTAO/FF) | D81: ='Flux Trésorerie'!I17/'Cpte Résultat'!I40 -> 7.2083333 | F81: ='Flux Trésorerie'!K17/'Cpte Résultat'!K40 -> 8.6010363 | H81: =(D81-F81)/F81 -> -0.16192269
A82: Solvabilité globale Risque liquidatif ( Ressources Propres/Total Bilan)>25% | D82: =Bilan!T22/Bilan!T39 -> 0.68522484 | F82: =Bilan!V22/Bilan!V39 -> 0.66069429 | H82: =(D82-F82)/F82 -> 0.037128443
A83: Liquidité général (Ratio de FR= Actifs circulants/ Passifs circulants)>1 | D83: =Bilan!K33/Bilan!T34 -> 0.84677419 | F83: =Bilan!M33/Bilan!V34 -> 0.83333333 | H83: =(D83-F83)/F83 -> 0.016129032
A84: Rentabilité d'exploitation par rapport au CA (EBE/ CA)>30% | D84: =D12/D15 -> 5.9923664 | F84: =F12/F15 -> 5.8776947 | H84: =(D84-F84)/F84 -> 0.019509645
A85: Rentabilité économique ( REX/ACTIF) >10% | D85: =D16/Bilan!K39 -> 0.2970852 | F85: =F16/Bilan!M39 -> 0.24741836 | H85: =(D85-F85)/F85 -> 0.2007403
A86: Rentabilité Financière (CP/RN)>10% | D86: =Bilan!T22/'INDICATEURS FIN'!D20 -> 5.3333333 | F86: =Bilan!V22/'INDICATEURS FIN'!F20 -> 5.9 | H86: =(D86-F86)/F86 -> -0.096045198
A87: Capacité d'endettement (Ressources Propres/Dettes structurelles)>1 | D87: =Bilan!T22/(Bilan!T23+Bilan!T24) -> 4 | F87: =Bilan!V22/(Bilan!V23+Bilan!V24) -> 2.95 | H87: =(D87-F87)/F87 -> 0.3559322
A88: Délai Client ( (créances client /CA)*365) | D88: =(Bilan!K31/'INDICATEURS FIN'!D12)*365 -> 13.949045 | F88: =(Bilan!M31/'INDICATEURS FIN'!F12)*365 -> 13.66018 | H88: =(D88-F88)/F88 -> 0.021146497
A89: Délai Fournisseur ( (dettes fournisseurs /Achats à crédit)*365) | D89: =(Bilan!T30/('Cpte Résultat'!I23+'Cpte Résultat'!I25))*365 -> 243.33333 | F89: =(Bilan!V30/('Cpte Résultat'!K23+'Cpte Résultat'!K25))*365 -> 219 | H89: =(D89-F89)/F89 -> 0.11111111
A90: Délai d'Ecoulement des Stocks ((stock moyen/Coût des produits vendus)*365 ) | D90: =+(D76/D77)*365 -> 0 | F90: =(F76/F77)*365 -> 0 | H90: =(D90-F90)/F90 -> #DIV/0!

Sheet GRILLE SOUCHE
A1: Désignation de l'entité: | B1: =+Bilan!D2 -> ELESYST SA | G1: Exercice clos le 31/12/ | H1: =+Bilan!Q2 -> 2019
A2: Numéro d'identification: | B2: =+Bilan!D3 -> MO1779U7P00197 | G2: Durée (en mois): | H2: =+Bilan!Q3 -> 12
A4: CRITERES PRINCIPAUX | B4: PONDERATION | C4: N° SOUS-CRITERES | G4: 1 | H4: 2 | I4: 3 | J4: 4 | K4: 5 | L4: 6 | M4: 7 | N4: 8 | O4: 9 | P4: 10
A5: ACTIVITE | B5: 0.1 | C5: 1 | D5: Positionnement concurentiel sur le marché* | G5: Très significatif | H5: Significatif | I5: Bon | J5: Plutôt Bon | K5: Moyen | L5: Plutôt Moyen | M5: Faible | N5: Limité | O5: Mauvais | P5: Très Mauvais
C6: 2 | D6: Tendance structurelle du marché | G6: Très bonne | H6: Très bonne | I6: Bonne | J6: Moyenne | K6: Faible | L6: Plutôt | M6: Plutôt | N6: En baisse | O6: En forte | P6: Secteur en difficulté
L7: en stagnation | M7: en baisse | N7: sensible | O7: baisse | P7: ou en déclin
C8: 3 | D8: Marchés cycliques ou à prix volatils | G8: Non | H8: Non ou très peu | I8: Peu | J8: Légèrement | K8: Modérément | L8: Modérément | M8: Fortement | N8: Fortement | O8: Très fortement | P8: Très fortement
C9: 4 | D9: Portefeuille produit | G9: Exremement bien | H9: Très bien | I9: Plutôt bien | J9: Assez bien | K9: Moyennement | L9: Moyennement | M9: Plutôt mal positionné | N9: Mal positionné | O9: Renouvellement | P9: Obsolescence
G10: positionné | H10: positionné | I10: positionné | J10: positionné | K10: positionné | L10: positionné | M10: et/ou étroit | N10: et/ou très étroit | O10: non assuré | P10: marquée
C11: 5 | D11: Pression liée à la clientèle | G11: Très | H11: Modérée | I11: Plutôt | J11: Plutôt | K11: Assez | L11: Sensible | M11: Assez | N11: Forte | O11: Très | P11: Extrêmement
G12: modérée | I12: Faible | J12: sensible | K12: sensible | M12: forte | O12: forte | P12: Forte
C13: 6 | D13: Barrière à l'entrée | G13: Très élevées | H13: Très élevées | I13: Elevées | J13: Assez élevées | K13: Plutôt faibles | L13: Faibles | M13: Très faibles | N13: Très faibles | O13: Inexistantes | P13: Inexistantes
C14: 7 | D14: Visibilité du secteur | G14: Très bonne | H14: Très bonne | I14: Bonne | J14: Bonne | K14: Moyenne | L14: Limitée | M14: Plutôt faible | N14: Faible | O14: Très faible | P14: Extrêmement faible
A16: GESTION ET STRATEGIE | B16: 0.2 | C16: 8 | D16: Qualite du profil du dirigeant | G16: Excellente | H16: Très bonne | I16: Bonne | J16: Assez bonne | K16: Moyennes | L16: Plutôt moyenne | M16: mauvaise | N16: Limitées | O16: Très mauvaise | P16: très mauvaise
C17: 9 | D17: Qualité de l'organisation | G17: Excellente | H17: Très bonne | I17: Bonne | J17: Assez bonne | K17: Moyennes | L17: Plutôt moyenne | M17: mauvaise | N17: Limitées | O17: Très mauvaise | P17: très mauvaise
C18: 10 | D18: Qualité du système de contrôle interne | G18: Excellente | H18: Très bonne | I18: Bonne | J18: Assez bonne | K18: Moyennes | L18: Plutôt moyenne | M18: mauvaise | N18: Limitées | O18: Très mauvaise | P18: très mauvaise
C19: 11 | D19: Qualité de la Stratégie commerciale et marketing | G19: Excellente | H19: Très bonne | I19: Bonne | J19: Assez bonne | K19: Moyennes | L19: Plutôt moyenne | M19: mauvaise | N19: Limitées | O19: Très mauvaise | P19: très mauvaise
C20: 12 | D20: Qualité desMoyens humains et techniques | G20: Excellente | H20: Très bonne | I20: Bonne | J20: Assez bonne | K20: Moyennes | L20: Plutôt moyenne | M20: mauvaise | N20: Limitées | O20: Très mauvaise | P20: très mauvaise
C21: 13 | D21: Adéquation des investissements / Impact sur l'emploi | G21: Important | H21: Importants | I21: Assez | J21: Suffisants | K21: Suffisants | L21: Plutôt faibles | M21: Faibles | N21: Insuffisants | O21: Très insuffisants | P21: Très insuffisants
G22: bien adaptés | H22: adaptés | I22: importants
C23: 14 | D23: Maîtrise des coûts de productivité / Impact la création de richesses | G23: Excellente | H23: Très bonne | I23: Bonne | J23: Assez bonne | K23: Moyennes | L23: Plutôt faible | M23: Faibles | N23: Limitées | O23: Très limitée | P23: Inexistantes
C24: 15 | D24: Cohérence des options stratégiques / Impact sur l'environnement | G24: Très cohérents | H24: Cohérents | I24: Plutôt | J24: Plutôt | K24: Moyennement | L24: Pas toujours | M24: Peu cohérents | N24: Peu ou pas cohérents | O24: Pas cohérents | P24: Pas cohérents
G25: dans l'ensemble | I25: cohérents | J25: cohérents | K25: cohérents | L25: cohérents | N25: ou non communiquées
C26: 16 | D26: Qualité des relations sociales | G26: Excellente | H26: Très bonne | I26: Bonne | J26: Assez bonne | K26: Moyennes | L26: Plutôt faible | M26: Faibles | N26: Limitées | O26: Très limitée | P26: Inexistantes
C27: 17 | D27: Succession des Dirigeants | M27: Se pose à M.T. | N27: Se pose à C.T. | O27: Problème aigu | P27: Problème aigu
M28: relève non prévue | N28: relève non assurée | O28: de succession | P28: de succession
A31: FINANCES | B31: PONDERATION | C31: N° SOUS-CRITERES | D31: SOUS-CRITERES | F31: REFERENCE | G31: 1 | H31: 2 | I31: 3 | J31: 4 | K31: 5 | L31: 6 | M31: 7 | N31: 8 | O31: 9 | P31: 10
A32: STRUCTURE FINANCIERE | B32: 0.45 | C32: 18 | E32: Dynamique de l'Equilibre Financier (FR/BFR) | F32: > 1 | G32: (> 2) | H32: ]2 ; 1,8] | I32: ]1,8 ; 1,6 ] | J32: ]1,6 ; 1,4 ] | K32: ]1,4 ; 1,2 ] | L32: ]1,2 ; 1] | M32: ]1 ; 0,8 ] | N32: ]0,8 ; 0,5 ] | O32: ]0,5 ; 0,2 ] | P32: (< 0,2)
C33: 19 | E33: Ratio d'endettement global ((Actifs - Capitaux propres)/ Actifs) <1 | F33: < 1 | G33: (< 0,1) | H33: ]0,1;0,2[ | I33: 0.3 | J33: ]0,4 ; 0,45 ] | K33: ]0,45 ; 0,49 ] | L33: 0.5 | M33: 0.6 | N33: 0.7 | O33: ]0,8 ; 1 ] | P33: (> 1)
A34: LIQUIDITE ET SOLVABILITE | C34: 20 | E34: Capacité de Remboursement (DLMT/CAFG) | F34: < 3 | G34: (< 1) | H34: ]1; 1,5 ] | I34: ]1,5 ; 2] | J34: ]2 ; 3 ] | K34: ]3 ; 3,4 ] | L34: ]3,4 ; 3,8 ] | M34: ]3,8 ; 4 ] | N34: ]4 ; 4,4 ] | O34: ]4,4 ; 5 ] | P34: (> 5)
C35: 21 | E35: Couverture des frais financiers (FTAO/FF) | F35: >3 | G35: >6 | H35: >5 | I35: >4 | J35: >3 | K35: =3 -> 3 | L35: <3 | M35: <2 | N35: <1,5 | O35: <1 | P35: <0,5
C36: 22 | E36: Solvabilité globale Risque liquidatif ( Ressources Propres/Total Bilan) | F36: >25% | G36: >35% | H36: >30% | I36: >25% | J36: =25% | K36: <25% | L36: <20% | M36: <15% | N36: <10% | O36: <5% | P36: <3%
C37: 23 | E37: Liquidité générale (Ratio de FR= Actifs circulants/ Passifs circulants)>1 | F37: > 1 | G37: ( > 2) | H37: ]2 ; 1,8 ] | I37: ]1,8 ; 1,6 ] | J37: ]1,6 ; 1,4 ] | K37: ]1,4 ; 1,2 ] | L37: ]1,2 ; 1 ] | M37: ]1 ; 0,8 ] | N37: ]0,8 ; 0,5 ] | O37: ]0,5 ; 0,2 ] | P37: (< 0,2)
A38: PERFORMANCE DE L'ACTIVITE ET RENTABILITE | C38: 24 | E38: Rentabilité d'exploitation par rapport au CA (EBE/ CA) | F38: > 30% | G38: >50% | H38: >45% | I38: >40% | J38: >35% | K38: >30% | L38: =30% | M38: <30% | N38: <25% | O38: <15% | P38: <10%
C39: 25 | E39: Rentabilité économique ( REX/ACTIF) | F39: > 10% | G39: >20% | H39: >17,5% | I39: >15% | J39: >12,5% | K39: =10% | L39: <10% | M39: <7,5% | N39: <5% | O39: <3% | P39: <1%
C40: 26 | E40: Rentabilité Financière (RN/Capitaux propres) | F40: > 10% | G40: >20% | H40: >17,5% | I40: >15% | J40: >12,5% | K40: =10% | L40: <10% | M40: <7,5% | N40: <5% | O40: <3% | P40: <1%
C41: 27 | E41: Capacité d'endettement (Ressources Propres/Dettes structurelles)>1 | F41: >1 | G41: ( > 2) | H41: ]2 ; 1,8 ] | I41: ]1,8 ; 1,6 ] | J41: ]1,6 ; 1,4 ] | K41: ]1,4 ; 1,2 ] | L41: ]1,2 ; 1 ] | M41: ]1 ; 0,8 ] | N41: ]0,8 ; 0,5 ] | O41: ]0,5 ; 0,2 ] | P41: (< 0,2)
A42: OUTILS D'AJUSTEMENT | C42: 28 | E42: Délai Client ( (créances client /CA)*365) | F42: < 90 Jours | G42: (< 10) | H42: [10 ; 20 ] | I42: ]20 ; 30 ] | J42: ]30 ; 40] | K42: ]40 ; 50 ] | L42: ]50 ; 60 ] | M42: ]60 ; 700 ] | N42: ]70 ; 80 ] | O42: ]80 ; 90 ] | P42: ( >90 )
C43: 29 | E43: Délai Fournisseur ( (dettes fournisseurs /Achats à crédit)*365) | F43: > 90 jours | G43: ( >90 ) | H43: [90 ; 80 ] | I43: ]80 ; 70 ] | J43: ]70 ; 60 ] | K43: ]60 ; 50 ] | L43: ]50 ; 40 ] | M43: ]40 ; 30 ] | N43: ]30 ; 20 ] | O43: ]20 ; 10 ] | P43: (< 10)
C44: 30 | E44: Délai d'Ecoulement des stocks ( (stock moyen/Coûts des produits vendus)*365 ) | F44: < 90 jours | G44: (< 20) | H44: [20 ; 40 ] | I44: ]40 ; 60 ] | J44: ]60 ; 80 ] | K44: ]80 ; 100 ] | L44: ]100 ; 120 ] | M44: ]120 ; 140 ] | N44: ]140 ; 160 ] | O44: ]160 ; 180 ] | P44: (>180 )
A46: QUALITE DE L'INFORMATION FINANCIERE ET GARANTIES | B46: 0.25 | C46: 31 | D46: Fiabilité des prévisions / Evolution des produits & charges | G46: Très fiable | H46: Fiable | I46: Plutôt fiable | J46: Plutôt fiable | K46: Moyennement fiable | L46: Pas toujours fiable | M46: Peu fiable | N46: Peu ou pas fiable | O46: Pas fiable | P46: Pas fiable
C47: 32 | D47: Représentation fidèle réalité comptable et financière/ Transparence des transactions | G47: Excellente | H47: Très bonne | I47: Bonne | J47: Assez bonne | K47: Moyennes | L47: Plutôt moyenne | M47: mauvaise | N47: Limitées | O47: Très mauvaise | P47: très mauvaise
C48: 33 | D48: Implication du dirigeant / Surface financière des promoteurs | G48: Très facile | H48: Facile | I48: Facile en | J48: Limité | K48: Limité | L48: Incertain mais | M48: Difficile mais | N48: Très peu | O48: Non | P48: Non
G49: en permanence | H49: conjoncture normale | L49: envisageable | M49: possible | N49: probable | O49: Pas d'appui | P49: Pas d'appui
C50: 34 | D50: Qualité des garanties & Actifs cessibles | G50: Oui, rapidement | H50: Oui, assez rapidement | I50: Oui, sous délai | J50: Oui, sous délai | K50: Surface financière | L50: Surface financière | M50: Surface financière | N50: Patrimoine | O50: Non, pas de | P50: Non, pas du tout
G51: et importants | H51: et assez importants | K51: limitée | L51: faible | M51: très faible | N51: insignifiant | O51: patrimoine perso | P51: de patrimoine
C53: NOTES MOYENNES DES CRITERES ET SOUS-CRITERES | G53: 1 | H53: 2 | I53: 3 | J53: 4 | K53: 5 | L53: 6 | M53: 7 | N53: 8 | O53: 9 | P53: 10
C54: COTATION INTERNATIONALE EQUIVALENTE | G54: AAA à AA- | H54: A+ à A- | I54: BBB+ et BBB | J54: BBB- | K54: BB+ | L54: BB | M54: BB- | N54: B+ | O54: B et B- | P54: CCC à C
C56: INTERVALLES DES NOTES MOYENNES DES CRITERES ET SOUS-CRITERES | G56: [1; 1,5] | H56: ]1,5; 2,5] | I56: ]2,5 ; 3] | J56: ] 3 ; 4] | K56: ] 4 ; 5] | L56: ]5 ; 6] | M56: ]6 ; 7] | N56: ]7 ; 8] | O56: ] 8 ; 9] | P56: ]9 ; 10]
C57: COTATION ELESYST EQUIVALANT A LA NOTATION DES PME | G57: SME1 | H57: SME2 | I57: SME3 | J57: SME4 | K57: SME5 | L57: SME6 | M57: SME7+ | N57: SME7 | O57: SME8 | P57: SME8-
A59: * Répondre en utilisant la grille "Taille du marché et positionnement de l'entreprise sur le marché" (onglet Marché sous Excel)

Sheet MARCHE
A1: Taille du marché et Positionnement de l'entreprise sur le marché
A2: TYPE DE MARCHE (1) position sur le marché | B2: Mondial ou géographiquement très diversifié (2) | C2: REGIONALE OU Zone géographique diversifiée (3) | D2: Local / PAYS
A3: Significatif | B3: 1 à 2 | C3: 3 à 4 | D3: 4 à 5
A4: Faible (5) | B4: 3 à 4 | C4: 4 à 7 | D4: 8 à 10
A8: Note des valeurs du sous-critère PSLM | B8: Valeur Sous-critère | C8: Commentaires
A9: 1 | B9: ='GRILLE SOUCHE'!G5 -> Très significatif | C9: Marché mondial ou géographiquement très diversifié et parts de marché significatives
A10: 2 | B10: ='GRILLE SOUCHE'!H5 -> Significatif | C10: Marché mondial ou géographiquement diversifié et parts de marché importantes
A11: 3 | B11: ='GRILLE SOUCHE'!I5 -> Bon | C11: Marché régional ou zone géographique diversifiée et parts de marché significatives
A12: 4 | B12: ='GRILLE SOUCHE'!J5 -> Plutôt Bon | C12: Marché régional ou zone géographique diversifiée et parts de marché faibles
A13: 5 | B13: ='GRILLE SOUCHE'!K5 -> Moyen | C13: Marché local/National et parts de marché significatives
A14: 6 | B14: ='GRILLE SOUCHE'!L5 -> Plutôt Moyen | C14: Marché local/National et parts de marché importantes
A15: 7 | B15: ='GRILLE SOUCHE'!M5 -> Faible | C15: Marché local ou zone géographique peu diversifiée et parts de marché moyennes
A16: 8 | B16: ='GRILLE SOUCHE'!N5 -> Limité | C16: Marché local ou zone géographique peu diversifiée et parts de marché faibles
A17: 9 | B17: ='GRILLE SOUCHE'!O5 -> Mauvais | C17: Marché local non diversifié et parts de marché faibles
A18: 10 | B18: ='GRILLE SOUCHE'!P5 -> Très Mauvais | C18: Marché étroit et parts de marché faibles

Sheet DEFINITION DES NOTES
A1: Note moyenne des critères et sous-critères d'analyse
A2: Définitions générales
A3: SME1 Excellent Situation économique et financière et visibilité excellentes : forte position sur ses marchés, faible endettement par rapport aux fonds propres et au cash flow, peu sensible aux aléas conjoncturels (grande stabilité de la situation financière et des résultats à travers les cycles de son industrie et de l'économie en général). Sa taille et sa situation lui donnent un accès très facile aux marchés financiers. La capacité du débiteur à exécuter ses engagements financiers est TRES FORTE | C3: SME6 Acceptable Les risques sectoriels, financiers et économiques sont importants mais devraient être compensés par les fondamentaux du débiteur. Possibilité limitée de trouver des financements en dehors de ses banques. La qualité du management est un élément important de la décision. Les opérations doivent être structurées (garanties, covenants) pour limiter le risque et la rémunération doit être accrue pour tenir compte de la prime de risque plus élevée.
A5: SME2 Très Bon La situation financière et le niveau de cash flow actuels sont très bons, avec un historique montrant une bonne stabilité, mais avec une légère sensibilité aux aléas conjoncturels. Endettement modéré par rapport aux fonds propres et au cash flow. Solide position sur ses marchés. Très bonne visibilité à court et moyen terme. Accès facile aux marchés financiers. Sa capacité à exécuter ses engagements financiers est FORTE. | C5: SME7 Potentiellement vulnérable Endettement important pour le secteur. Les risques sectoriels, financiers et économiques sont importants et insuffisamment compensés par les fondamentaux du débiteur qui ne présentent pas une qualité, une stabilité et une visibilité suffisantes. Ce niveau nécessite un suivi attentif. La qualité du management est un élément primordial de la décision. Ce niveau nécessite une grande exigence dans la structuration des opérations et une rémunération significative.
A7: SME3 Bon Situation financière et cash flow convenables mais montrant quelque volatilité, et qui pourraient être affaiblis par une conjoncture (cycle) ou des évènements défavorables dont l'occurrence est possible. Endettement par rapport aux fonds propres et au cash flow dans la moyenne. Bonne visibilité à court et moyen terme. Possibilité d'accéder à de nouveaux financements dans une conjoncture normale. Cette note s'applique aussi aux PME dont la situation financière est solide mais qui sont exclues des catégories précédentes en raison de leur taille. | C7: SME7- Vulnérable Une aggravation des risques économiques et financiers qui pèsent sur le débiteur le conduirait vraisemblablement à faire défaut sur ses engagements financiers. De nouvelles opérations ne peuvent être envisagées qu'avec une extrême rigueur dans la structuration et uniquement dans le cadre de politiques de crédit dûment autorisées.
A9: SME4 Assez Bon Situation financière et cash flow moyens, avec une plus grande volatilité de la situation financière et du cash flow. Il existe quelques facteurs de risque qui pourraient affaiblir la capacité du débiteur à exécuter ses engagements financiers. Cependant, visibilité satisfaisante à court et moyen terme. Accès restreint aux marchés financiers et plus coûteux, mais possibilité de développement des engagements avec ses banques. | C9: SME8 Très vulnérable En l'absence d'amélioration de l'environnement (conjoncture et marché), et/ou de mesures drastiques de restructuration industrielle ou financière, la survie de l'entreprise serait en question. Ce niveau doit être suivi de près et assorti d'objectifs précis pour réduire les risques (réduction des concours, garanties, etc.). Normalement, il exclut une entrée en relation ou un accroissement des engagements.
A11: SME5 Moyen Cash flow suffisant pour le service de la dette. Les incertitudes sur les fondamentaux du débiteur et son exposition à divers risques (sectoriels, financiers, économiques) peuvent affecter à terme sa capacité à s'acquitter de ses obligations. Visibilité satisfaisante à court terme mais moins claire à moyen terme. Un accroissement des engagements auprès de ses banques reste encore envisageable. La qualité du management est un élément important de la décision. Accès aux marchés financiers limité, restreint et plus coûteux. | C11: SME8- Douteux et/ou compromis L'existence d'échéances financières impayées en principal et/ou en intérêts depuis plus de 3 mois entraîne le classement dans cette catégorie. Les débiteurs les plus faibles de cette catégorie sont dans une situation nettement dégradée et préoccupante quant à la bonne fin des crédits. Un dépôt de bilan est fortement possible. Ce niveau doit être suivi de très près. Le suivi doit être assortie d'objectifs précis (réduction des concours, amélioration des garanties, etc.). La gestion doit être centralisée (prise en charge par les équipes spécialisées dans la prévention de la défaillance).

Sheet NOTATION ELESYST DES PME
A1: Notation conventionnelle des PME adoptée par ELESYST
A2: Définitions générales
A4: SAVSME CMR SME1 Le niveau de solvabilité de la PME, validé en comparaison d'autres PME, est très élevé
A6: SAVSME CMR SME2 Le niveau de solvabilité de la PME, validé en comparaison d'autres PME, est élevé
A8: SAVSME CMR SME3 Le niveau de solvabilité de la PME, validé en comparaison d'autres PME, est au dessus de la moyenne
A10: SAVSME CMR SME4 Le niveau de solvabilité de la PME, validé en comparaison d'autres PME, est moyen
A12: SAVSME CMR SME5 Le niveau de solvabilité de la PME, validé en comparaison d'autres PME, est en dessous de la moyenne
A14: SAVSME CMR SME6 Le niveau de solvabilité de la PME, validé en comparaison d'autres PME, est insuffisant
A16: SAVSME CMR SME7 Le niveau de solvabilité de la PME, validé en comparaison d'autres PME, est bas
A18: SAVSME CMR SME8 Le niveau de solvabilité de la PME, validé en comparaison d'autres PME, est très bas. La PME présente un risque important de défaut.

Sheet COMMENTAIRES annexes
A1: Nom de la société: Secteur d'activité: Nom du Dirigeant:
A2: Effectif employés: Année de création:
A3: CRITERES | B3: N° SOUS-CRITERES | C3: SOUS-CRITERES | D3: COMMENTAIRES
A4: ACTIVITE | B4: 1 | C4: Positionnement concurentiel sur le marché | D4: Permet d'apprécier le pouvoir de négociation de l'entreprise sur les marchés, les parts de marchés acquises, et sa capacité à innover.
B5: 2 | C5: Tendance structurelle du marché | D5: Renvoie à l’évolution du marché sur lequel l’entreprise se situe (croissance, stagnation, déclin) et de ce fait sa capacité à développer son activité.
B6: 3 | C6: Marchés cycliques ou à prix volatils | D6: Les marchés cycliques sont caractérisés par des périodes de croissance suivies de repli plus ou moins prononcées et plus ou moins rapprochées. Les marchés à prix volatils sont ceux liés aux matières premières dont les prix sont sujets à de fortes variations.
B7: 4 | C7: Portefeuille produit | D7: Ce critère permet de porter un jugement sur la capacité de l’entreprise à diversifier et adapter son offre de produits sur le marché. Il s'agit d'évaluer son niveau de maitrise de sa politique de gestion du cycle de vie de ses produits (Matrice BCG).
B8: 5 | C8: Pression liée à la clientèle | D8: Appreciation du risque lié à la pression de la clientèle directe de l'entreprise (client représentant 10% de son CA) : diversifiée ou concentrée, fidélisée ou non récurrente, rapport de force de bonne ou mauvaise qualité.
B9: 6 | C9: Barrière à l'entrée | D9: Ensemble des inerties qui peuvent constituer un frein à la création ou à l'exercice de l'activité de l'entreprises.
B10: 7 | C10: Visibilité du secteur | D10: Tenir compte des changements possible de la réglementation, de la qualité de l'environnement du pays dans lequel l'entreprise opère (viabilité du système législatif, qualité du système politique, environnement social)
A11: GESTION & STRATEGIE | B11: 8 | C11: Qualité du profil du drigeant | D11: L’expérience des promoteurs dans les affaires (dans un secteur d’activité représentatif) et l’historique des opérations de l’entité étudiée constituent des critères essentiels pour évaluer la compétence managériale. Un manager doté d’une expérience de plusieurs cycles d’activités et familiarisé à la mise en œuvre des projets, bénéficie d’un avantage certain. De même, l’expérience dans la conquête de la clientèle, les nouvelles initiatives commerciales et le niveau de priorité accordé à la fonction financière sont également des critères vitaux. Un poids conséquent doit être accordé à l’historique du promoteur dans la réalisation des projets et le statut desdits projets, incluant la réussite du montage financier. Enfin le profil moral des dirigeants doit être systématiquement questionné en intégrant des critères socio-anthropologiques liés aux différents réseaux sociaux et professionnels avec lesquels ils interagissent.
B12: 9 | C12: Qualité de l'organisation | D12: La maîtrise des processus métiers et administratifs de l'entité doit être matérialisée à travers les procédures et les textes organiques couvrant tous les pans fonctionnels. Au-delà de l'existence de ces textes, il est important de vérifier qu'ils sont connus et mis en application par les principaux responsables et l'ensemble du personnel.
B13: 10 | C13: Qualité du système de contrôle interne | D13: Il s'agit d'apprecier l'organisation des ressources qui permettent de collecter, stocker, traiter et distribuer les informations nécessaires à une prise de décisions , le suivi et le contrôle des activité de l'entreprise.
B14: 11 | C14: Qualité de la Stratégie commerciale et marketing | D14: Ce critère permet d'évaluer les actions menées par l'entreprise afin de d'accroître ses parts de marché et donc par conséquent developper son portefeuille client.
B15: 12 | C15: Qualité des Moyens humains et techniques | D15: Appréciation de la stratégie en terme de clarté et de pérénnité de l'entreprise, de cohérence entre qualité des investisssements, corps de metiers identifiés, perspectives de marché et action des concurrents.
B16: 13 | C16: Adéquation des investissements / Impact sur l'emploi | D16: Apprecier si les investissements consentis par l'entreprise permettent de réaliser en quantité et en qualité les biens et services souhaités par cette dernière et si l'impact sur la création et la préservation des emplois est positif.
B17: 14 | C17: Maîtrise des coûts de productivité / Impact sur la création des richesses | D17: Evaluer la capacité de l'entreprise à minimiser ses coûts de production tout en réalisant des gains supplémentaires. Apprécier sa capacité à créer des richesses nouvelles.
B18: 15 | C18: Cohérence des options stratégiques / Impact sur l'environnement | D18: Il importe qu'à la création d'une entreprise ou au début de chaque nouvel exercice, de s'assurer de la cohérence des décisions stratégiques prises par les dirigeants concernant : l'activité, les moyens de production, les ressources humaines et les finances. Une inadéquation entre ces décisions constitue une source importante de risque de pertes pour l'entreprise. L'impact environnemental des options stratégiques retenues doit influencer l'évaluation.
B19: 16 | C19: Qualité des relations sociales | D19: Appreciation du climat social, de la politique de gestion des ressources humaine, du niveau de turn-over du personnel. Des entretiens avec toutes les catégories du personnel sont indispensables pour cerner la qualité du climat.
B20: 17 | C20: Succession des Dirigeants | D20: Il s'agit d'évaluer dans quelle mesure le risque lié aux droits de succession est encadré au sein de l'entreprise, ce qui permet d'assurer la pérénité de son patrimoine.
A21: FINANCES | B21: 18 | C21: Dynamique de l'équilibre financier (FR / BFR >= 1) | D21: Elle permet d'apprécier l'évolution de l'équilibre financier dans le temps (la situation d'équilibre financier étant la couverture de l'ensemble des besoin liés à l'exploitation par le fond de roulement). Un ratio de structure financière de 0,5 est considéré comme acceptable. Cela signifie que le FR couvre au moins la moitié du BFR.
B22: 19 | C22: Ratio d'endettement global ((Actifs - Capitaux propres)/ Actifs) <1 | D22: Il permet d'apprécier la niveau de d'endettement de l'entreprise et sa soutenntabilité. Il compare la dette d’une entreprise à ses actifs, ce qui donne alors une idée du levier qu’utilise cette dernière pour fonctionner. Il est égal à : (Actifs - Capitaux propres) / Actifs Un ratio faible traduit une faible dépendance à l’égard de la dette, autrement dit, l’entreprise n’a pas un besoin vital de faire appel aux capitaux d’agents extérieurs (banques) pour opérer. Plus le ratio est faible, plus l’entreprise fait appel à ses propres capitaux pour fonctionner (autofinancement). Plus le ratio est élevé, plus l’entreprise a une comptabilité risquée. Si un ratio démesurément élevé peut mettre en péril la solvabilité de l’entreprise, il peut également masquer un sous-investissement de celle-ci, et donc, un potentiel décrochage en termes de compétitivité. Un ratio d’endettement de 0,50 est considéré comme acceptable. Cela signifie que l’entreprise possède deux fois plus d’actifs que de dettes. Ou, exprimé différemment, les dettes ne représentent que la moitié des actifs. En d’autres termes, les créditeurs de l’entreprise possèdent la moitié des actifs de celle-ci, tandis que les actionnaires détiennent l’autre moitié.
B23: 20 | C23: Capacité de remboursement (DLMT/ CAFG) < 3 | D23: Il exprime la disposition de l'entreprise à rembourser son endettement net au moyen de sa capacité d'autofinancement. Il permet de mesurer le nombre d'années de CAFG necessaire à l'entreprise pour rembourser, par ses propres moyens, la totalité de ses dettes. Un ratio de capacité de remboursement de 3 est considéré comme acceptable.
B24: 21 | C24: Couverture des frais financiers (FTAO/FF)> 3 | D24: Ce ratio est exprimé en un chiffre, qui indique combien de fois les intérêts sont couverts par les flux de trésorerie des activités ordinaires. Un ratio de couverture inférieur à 3 signale que la marge de sécurité de l'entreprise est insuffisante. Un ratio égal à 3 est considéré comme un minimum. Il permet d'évaluer la capacité de l'entreprise à rembourser les charges financières à partir de ses ressources d'exploitation.
B25: 22 | C25: Solvabilité globale - Risque liquidatif (Ressources Propres/Total Bilan) > 25% | D25: C'est la mesure de la solvabilité globale de l'affaire : les ressources propres doivent être suffisantes pour supporter une certaine dévalorisation de l'actif tel qu'il figure au bilan. La comparaison du niveau des ressources propres par rapport au total du bilan est une mesure du degré d'engagement des actionnaires dans le risque d'entreprise. On considère que ce ratio doit excéder les 25% pour que l'entreprise ne soit pas trop endettée, on majorera ce chiffre pour le secteur industriel (35%) et on le minorera pour le secteur commercial (20%). Ce ratio mesure aussi, du point de vue des tiers à l'entreprise - hors associés et prêteurs - quelle dépréciation moyenne peut supporter l'actif avant que ces tiers ne soient amenés à assumer eux mêmes le risque d'entreprise.
B26: 23 | C26: Liquidité générale (Ratio de FR= Actifs circulants/ Passifs circulants)>1 | D26: Assimilable au fonds de roulement, ce ratio permet de savoir si une entreprise est capable d’assumer (ou pas) ses dettes à court terme en les mettant au regard de ses actifs à court terme. Ce ratio doit toujours être supérieur à 1. Plus il est élevé, plus la latitude dont dispose une société pour développer ses activités est grande. Sauf circonstances particulières, un ratio inférieur à 1 signifie que le fonds de roulement est négatif.
B27: 24 | C27: Rentabilité d'exploitation par rapport au CA (EBE/ CA)>30% | D27: Il permet d'apprecier la capacité de l'exploitation à dégager un revenu satisfaisant après couverture des charges directement liées à l'activité. L'EBE est indispensable pour apprécier la performance d’une société car il permet de mesurer les bénéfices et profits réalisés dans l’entreprise. Il est également très utilisé car n’étant pas affecté par la politique d’amortissement et de provision de l’entreprise. En anglais, on parle de Earnings Before Interest, Taxes, Depreciation and Amortization (EBITDA). Formule : Excédent Brut d'Exploitation = valeur ajoutée brute - frais du personnel (salaires + cotisations sociales) - impôts et taxes liés à la production (- participation des salariés, pour obtenir l’EBITDA) Le ratio EBE/CA, appelé marge d’EBE, permet d’apprécier le partage de la valeur ajoutée entre les actionnaires (qui sont rémunérés à partir de l'Excédent brut d'exploitation) et les salariés.
B28: 25 | C28: Rentabilité économique ou Return On Capital Employed (ROCE) (Résultat d'Exploitation / Total actifs) > 10% | D28: Permet d'apprecier le comportement de la rentabilité comparativement aux investissements de toute nature necessaires à l'exploitation de l'entreprise. C’est un ratio fondamental de l’analyse financière. Il représente l’efficacité avec laquelle l’entreprise utilise les capitaux mis à sa disposition et n’est pas affecté par la structure financière de l’entreprise. Le principal inconvénient de ce ratio est qu’il prend en compte la valeur comptable d’actifs qui se déprécient, alors que le résultat d’exploitation a tendance à croître avec l’inflation. Dans le cadre d’une comparaison d’entreprises ayant la même activité, les actifs les plus dépréciés auront une ROCE plus élevée, même si les actifs les plus récents sont peut-être plus efficaces. Un ratio de rentabilité économique de 10% est considéré comme acceptable.
B29: 26 | C29: Rentabilité financière (RN/ Capitaux Propres)>10% | D29: Egalement appelé «Return on Equity» (ROE), ce ratio permet de mesurer les profits dégagés par la société avec l’argent investi par les actionnaires. Il permet de comparer la profitabilité d’une société par rapport aux autres entreprises intervenant dans le même secteur d’activité. Ce ratio ne prend de sens qu’en fonction du secteur sur lequel l’entreprise intervient et en comparaison avec la norme sectorielle. Les secteurs qui nécessitent d’importants investissements de base font davantage appel aux actionnaires et inversement pour ceux ne requérant que peu d’infrastructures.
B30: 27 | C30: Capacité d'endettement (Ressources Propres/Dettes structurelles)>1 | D30: En règle générale, ce ratio doit être supérieur à 1. Il permet de s'assurer que les concours bancaires à long et moyen terme ne sont pas supérieurs à ceux des investisseurs associés au risque d'entreprise. Plus cette capacité d'endettement est importante, plus la société pourra avoir recours à l'emprunt pour financer des acquisitions ou investissements. Il convient cependant de modérer cette limite stricte en tenant compte des différents secteurs d'activité et de leurs spécificités. Les entreprises de négoce, par exemple, ont des ressources propres faibles et des engagements à court terme élevés. Dans ce cas le ratio acceptable pourra aller jusqu'à 0,1. On pourra calculer la marge théorique d'endettement de la façon suivante : Marge = Ressources propres - Dettes structurelles
B31: 28 | C31: Délai Moyen de Recouvrement des Comptes Clients | D31: Il permet de mesurer le nombre moyen de jours qu'il faut aux clients pour payer leurs factures. Il fournit également une indication de l'efficacité des politiques de crédit et de recouvrement en vigueur dans l'entreprise. Le nombre de jours dans l'exercice correspond au nombre de jours de la période à mesurer; il s'établit le plus souvent à 365. Formule : Délai de recouvrement des comptes-clients = 365 x solde moyen des comptes clients / chiffres d’affaires de l’exercice En comparant la durée obtenue par calcul avec la norme du secteur concerné, il est possible de savoir si l’entreprise est trop ou pas assez sévère quant aux délais accordés aux clients pour rembourser leur crédit. Si le ratio obtenu est inférieur à la norme, cela signifie que l’entreprise a une politique de crédit trop restrictive, avec pour conséquence le risque de perdre des clients, ou de la forcer, pour conserver ses clients, à accorder des rabais sur ses prix de vente ou encore des escomptes de caisse importantes. Si le nombre obtenu est supérieur à la norme, cela démontre une faiblesse dans le recouvrement des factures. Il est possible également que l’entreprise pratique l’affacturage. Dans ce cas, le poste Clients est minoré au profit de la trésorerie (VMP et disponible).
B32: 29 | C32: Délai Moyen de Règlement des Comptes Fournisseurs | D32: Il permet de mesurer le nombre de jours qu'il faut en moyenne à l'entreprise pour payer ses fournisseurs entre le moment où un achat est conclu et le moment où la facture est réglé. Le solde moyen des comptes fournisseurs correspond à la moyenne du solde d'ouverture et du solde de clôture des comptes fournisseurs pour l'ensemble de la période à mesurer. Délai moyen de règlement des comptes fournisseurs = 365 X solde moyen des comptes fournisseurs / achats à crédit Une politique de paiement des fournisseurs équilibrée permettra à l’entreprise de profiter au maximum du crédit mis à sa disposition (sans frais d’intérêt) ainsi que les escomptes de caisses offertes et de conserver sa réputation de crédit auprès des fournisseurs. Si la période de paiement de l’entreprise est inférieure à la norme ou période moyenne du secteur, c’est le signe probable que l’entreprise paie plus rapidement ses comptes fournisseurs que ceux-ci ne demandent de l’être. Par conséquent, elle se prive d’une partie de ses sources de financement gratuit que sont les comptes fournisseurs. Si la période de paiement est supérieure à la moyenne, ceci pourrait être le signe que l’entreprise éprouve des difficultés à honorer ses dettes et qu’elle se trouve, probablement, dans une situation risquée. L’objectif d’une entreprise est d’accorder le délai de paiement le plus court possible à ses clients et d’obtenir le délai de paiement le plus long de la part de ses fournisseurs.
B33: 30 | C33: Délai d'Ecoulement des Stocks | D33: Il permet de mesurer le nombre moyen de jours d’activités commerciales que l’entreprise peut satisfaire grâce à la quantité de marchandises qu’elle a en stock. Le stock moyen est la moyenne du solde d'ouverture et du solde de clôture de l'inventaire. Formule : Délai moyen d’écoulement des stocks = 365 X stock moyen / coût des produits vendus Si le ratio obtenu est inférieur à la norme du secteur, c’est que l’entreprise vend ses stocks très rapidement ou de plus ne plus rapidement. Si cela ne nuit pas à la croissance de l’entreprise, c’est le signe que les marchandises proposées au public sont bien acceptées et faciles à vendre. Si il est supérieur à la norme, cela signifie que les marchandises se vendent de moins en moins rapidement. C’est l’indice que le public accepte moins bien les produits ou que certaines marchandises dépréciées se sont accumulées dans les stocks ou qu’il y a eu des erreurs de planification de la production et/ou des achats.
A34: QUALITE DE L'INFORMATION FINANCIERE | B34: 31 | C34: Fiabilité des prévisions / Evolution produits & charges | D34: Appréciation de la fréquence de communication des prévisions par les dirigeants et évaluation du taux de réalisation de ces prévisions / Appréciation de l'évolution des produits et charges par rapport aux prévisions et àla conjoncture.
B35: 32 | C35: Représentation fidèle réalité comptable et financière/ Transparence des transactions | D35: Evaluation de la conformité des pratiques comptables et financières. Evaluation de la fidélité des informations comptables et financières par rapport à la réalité. Vérification de la conformité des transactions.
B36: 33 | C36: Implication du dirigeant / Surface financière des promoteurs | D36: Le dirigeant de l'entité doit veiller personnellement à la qualité de l'information comptable et financière de l'entité. Il doit pour cela être capable de comprendre les enjeux de l'organisation comptable et d'interpréter lui-même les résultats produits par les états financiers. Il doit également démontrer son engagement et sa détermination à assurer la transparence de ses transactions financières, et le cas échéant à apporter sa caution à l'entreprise.
B37: 34 | C37: Qualité des garanties & Actifs cessibles | D37: Ce sous-critère permet d'apprécier si l'entreprise et/ou ses promoteurs détiennent des actifs (corporels, incorporels, financiers,...) qu'ils peut céder ou offrir en garantie pour traverser une situation difficile, voire pour assurer sa croissance et bénéficier de financements extérieurs. Le jugement portera sur la rapidité possible des céssions, leur montant, et les plus ou moins value / Critère lié au profil du dirigeant et qui intègre la capacité de ce dernier à apporter une aide financière (apport en fonds propres) ou une caution (solidaire, hypothécaire ou financière).

Sheet listes annexes
A1: Positionnement concurrentiel sur le marché | B1: Tendance structurelle du marché | C1: Marchés cycliques ou à prix volatils | D1: Portefeuille produits | E1: Pression liée à la clientèle | F1: Barrieres à l'entree | G1: Visibilité du secteur | H1: Qualité des relations sociales | I1: Succession du dirigeant | J1: Qualité des prévisions | K1: Maîtrise des coûts de productivité / Impact sur la création de richesses | L1: Cohérence des options stratégiques / Impact sur l'environnement | M1: Adéquation des investissements / Impact sur l'emploi | N1: Qualité du profil du dirigeant | O1: Qualité de l'organisation | P1: Qualité du système de contrôle interne | Q1: Qualité de la stratégie commerciale et marking | R1: Qualité des moyens humains et techniques | S1: Fiabilité des prévisions/Evolution produits & charges | T1: Représentation fidèle de la réalité par l'information comptable et financière | U1: Implication du dirigeant/transparence transactions | V1: Actifs cessibles & Surface financière du dirigeant
A2: Très significatif | B2: très bonne A | C2: non | D2: extremement bien positionné | E2: très modérée | F2: très élevéés A | G2: très bonne A | H2: excellente | I2: Ne se pose pas du tout | J2: très fiables dans l'ensemble | K2: excellente | L2: très cohérents | M2: importants,bien adaptés | N2: excellente | O2: excellente | P2: excellente | Q2: excellente | R2: excellente | S2: très fiable | T2: excellente | U2: très facile en permanence | V2: oui, rapidement et importants
A3: Significatif | B3: très bonne B | C3: non ou très peu | D3: très bien positionné | E3: modérée | F3: très élevées B | G3: très bonne B | H3: très bonne | I3: Ne se pose pas | J3: plutôt fiables A | K3: très bonne | L3: cohérents | M3: importants,adaptés | N3: très bonne | O3: très bonne | P3: très bonne | Q3: très bonne | R3: très bonne | S3: fiable | T3: très bonne | U3: facile en conjoncture normale A | V3: oui, assez rapidement et assez importants
A4: Bon | B4: bonne | C4: peu | D4: plutot bien positionné | E4: plutôt faible | F4: élevées | G4: bonne A | H4: bonne | I4: Garantie par le cadre juridique et fonctionnel | J4: plutôt fiables B | K4: bonne | L4: plutôt cohérents A | M4: assez importants | N4: bonne | O4: bonne | P4: bonne | Q4: bonne | R4: bonne | S4: plutôt fiable A | T4: bonne | U4: facile en conjoncture normale B | V4: oui, sans delai A
A5: Plutôt Bon | B5: moyenne | C5: légèrement | D5: assez bien positionné | E5: plutot sensible | F5: assez élevées | G5: bonne B | H5: assez bonne | I5: Garantie par le cadre juridique | J5: fiables | K5: assez bonne | L5: plutôt cohérents B | M5: suffisants | N5: assez bonne | O5: assez bonne | P5: assez bonne | Q5: assez bonne | R5: assez bonne | S5: plutôt fiable B | T5: assez bonne | U5: limité en conjocture normale A | V5: oui, sans delai B
A6: Moyen | B6: faible | C6: modérement B | D6: moyennement positionné A | E6: assez sensible | F6: plutôt faibles | G6: moyenne à moyen terme | H6: moyenne | I6: Assurée depuis un certain temps (Moyen) | J6: moyennement fiables | K6: moyenne | L6: moyennement cohérents | M6: plutôt faibles | N6: moyenne | O6: moyenne | P6: moyenne | Q6: moyenne | R6: moyenne | S6: moyennement fiable | T6: moyenne | U6: limité en conjocture normale B | V6: Surface financière limitée
A7: Plutôt Moyen | B7: plutôt en stagnation | C7: modérement A | D7: moyennement positionné B | E7: sensible | F7: faibles | G7: limitée à moyen terme | H7: limitée | I7: Assurée depuis quelque temps (Court) | J7: pas toufours fiables | K7: plutôt faible | L7: pas toujours cohérents | M7: faibles | N7: plutôt moyenne | O7: plutôt moyenne | P7: plutôt moyenne | Q7: plutôt moyenne | R7: plutôt moyenne | S7: pas toujours fiable | T7: plutôt moyenne | U7: incertain mais envisageable | V7: Surface financière faible
A8: Faible | B8: plutôt en baisse | C8: fortement B | D8: plutôt mal positionné et/ou étroit | E8: assez forte | F8: très faibles A | G8: plutot faible | H8: plutôt faible | I8: se pose à moyen terme, relève non prévue | J8: peu fiables | K8: faible | L8: peu cohérents | M8: insuffisants A | N8: mauvaise | O8: mauvaise | P8: mauvaise | Q8: mauvaise | R8: mauvaise | S8: peu fiable | T8: mauvaise | U8: difficile mais possible | V8: Surface financière très faible
A9: Limité | B9: en baisse sensible | C9: fortement A | D9: mal positionné et/ou très étroit | E9: forte | F9: très faibles B | G9: faible | H9: faible | I9: se pose à court terme,relève non assurée | J9: peu ou pas fiables ou non communiquées | K9: limité | L9: peu ou pas cohérents | M9: insuffisants B | N9: limitée | O9: limitée | P9: limitée | Q9: limitée | R9: limitée | S9: peu ou pas fiable | T9: limitée | U9: très peu probable | V9: Patrimoine insignifiant
A10: Mauvais | B10: en forte baisse | C10: très fortement B | D10: renouvellement non assuré | E10: très forte | F10: inexistentes A | G10: très faible | H10: mauvaise | I10: problème aigue de succession | J10: pas fiables A | K10: très limitée | L10: pas cohérents A | M10: très insuffisants A | N10: très mauvaise A | O10: très mauvaise A | P10: très mauvaise A | Q10: très mauvaise A | R10: très mauvaise A | S10: pas fiable A | T10: très mauvaise A | U10: non pas d'appui A | V10: Non, pas patrimoine personnel
A11: Très Mauvais | B11: secteur en difficulté ou en déclin | C11: très fortement A | D11: obsolescence marquée | E11: extremement forte | F11: inexistentes B | G11: extrement faible | H11: très mauvaise | I11: gestion par administrateur | J11: pas fiables B | K11: inexistente | L11: pas cohérents B | M11: très insuffisants B | N11: très mauvaise B | O11: très mauvaise B | P11: très mauvaise B | Q11: très mauvaise B | R11: très mauvaise B | S11: pas fiable B | T11: très mauvaise B | U11: non pas d'appui B | V11: Non, pas de patrimoine du tout

Sheet Tendances et prévisions
A1: CRITERE ACTIVITE
A2: Sous-critères | B2: Question de notation | C2: Entreprise 1 | J2: Entreprise 2
C3: Périodes d'observation | F3: Prévisions | J3: Périodes d'observation | M3: Prévisions
C4: 1 | D4: 2 | E4: 3 | F4: 4 | G4: 5 | H4: 6 | J4: 1 | K4: 2 | L4: 3 | M4: 4 | N4: 5 | O4: 6
A5: Positionnement concurrentiel sur le marché | B5: Vos produits ou services s’adressent t’ils uniquement au marché local ? Si oui, comment est délimitée votre zone de vente ? | C5: 0 | D5: 0 | E5: 0 | F5: =TREND(C5:E5,C4:E4,F4:H4,) -> 0 | G5: =TREND(D5:F5,D4:F4,G4:H4,) -> 0 | H5: =TREND(E5:G5,E4:G4,H4:H4,) -> 0 | J5: 0 | K5: 0 | L5: 0 | M5: =TREND(J5:L5,J4:L4,M4:O4,) -> 0 | N5: =TREND(K5:M5,K4:M4,N4:P4,) -> 0 | O5: =TREND(L5:N5,L4:N4,O4:Q4,) -> 0
B6: Quelle est la situation de la concurrence dans votre secteur d’activité? | C6: 0 | D6: 0 | E6: 0 | F6: =TREND(C6:E6,C5:E5,F5:H5,) -> 0 | G6: =TREND(D6:F6,D5:F5,G5:H5,) -> 0 | H6: =TREND(E6:G6,E5:G5,H5:H5,) -> 0 | J6: 0 | K6: 0 | L6: 0 | M6: =TREND(J6:L6,J5:L5,M5:O5,) -> 0 | N6: =TREND(K6:M6,K5:M5,N5:P5,) -> 0 | O6: =TREND(L6:N6,L5:N5,O5:Q5,) -> 0
B7: Quelle est la situation de la concurrence dans votre secteur d’activité? | C7: 0 | D7: 0 | E7: 0 | F7: =TREND(C7:E7,C6:E6,F6:H6,) -> 0 | G7: =TREND(D7:F7,D6:F6,G6:H6,) -> 0 | H7: =TREND(E7:G7,E6:G6,H6:H6,) -> 0 | J7: 0 | K7: 0 | L7: 0 | M7: =TREND(J7:L7,J6:L6,M6:O6,) -> 0 | N7: =TREND(K7:M7,K6:M6,N6:P6,) -> 0 | O7: =TREND(L7:N7,L6:N6,O6:Q6,) -> 0
A8: Note sous-critère | C8: =(C5*0.4+C6*0.4+C7*0.2)*(10/6) -> 0 | D8: =(D5*0.4+D6*0.4+D7*0.2)*(10/6) -> 0 | E8: =(E5*0.4+E6*0.4+E7*0.2)*(10/6) -> 0 | F8: =(F5*0.4+F6*0.4+F7*0.2)*(10/6) -> 0 | G8: =(G5*0.4+G6*0.4+G7*0.2)*(10/6) -> 0 | H8: =(H5*0.4+H6*0.4+H7*0.2)*(10/6) -> 0 | J8: =(J5*0.4+J6*0.4+J7*0.2)*(10/6) -> 0 | K8: =(K5*0.4+K6*0.4+K7*0.2)*(10/6) -> 0 | L8: =(L5*0.4+L6*0.4+L7*0.2)*(10/6) -> 0 | M8: =(M5*0.4+M6*0.4+M7*0.2)*(10/6) -> 0 | N8: =(N5*0.4+N6*0.4+N7*0.2)*(10/6) -> 0 | O8: =(O5*0.4+O6*0.4+O7*0.2)*(10/6) -> 0
A9: Tendance structurelle du marché | B9: Pensez-vous que l’état actuel des environnements politique, social, législatif, du pays garantit le plein essor de votre activité ? | C9: 0 | D9: 0 | E9: 0 | F9: =TREND(C9:E9,C4:E4,F4:H4,) -> 0 | G9: =TREND(D9:F9,D4:F4,G4:H4,) -> 0 | H9: =TREND(E9:G9,E4:G4,H4:H4,) -> 0 | J9: 0 | K9: 0 | L9: 0 | M9: =TREND(J9:L9,J4:L4,M4:O4,) -> 0 | N9: =TREND(K9:M9,K4:M4,N4:P4,) -> 0 | O9: =TREND(L9:N9,L4:N4,O4:Q4,) -> 0
A10: Note sous-critère | C10: =(C9*1)*(10/6) -> 0 | D10: =(D9*1)*(10/6) -> 0 | E10: =(E9*1)*(10/6) -> 0 | F10: =(F9*1)*(10/6) -> 0 | G10: =(G9*1)*(10/6) -> 0 | H10: =(H9*1)*(10/6) -> 0 | J10: =(J9*1)*(10/6) -> 0 | K10: =(K9*1)*(10/6) -> 0 | L10: =(L9*1)*(10/6) -> 0 | M10: =(M9*1)*(10/6) -> 0 | N10: =(N9*1)*(10/6) -> 0 | O10: =(O9*1)*(10/6) -> 0
A11: Marchés cycliques ou à prix volatils | B11: Connaissez-vous des périodes d’inactivité? A quoi pensez-vous que cela est dû ? | C11: 0 | D11: 0 | E11: 0 | F11: =TREND(C11:E11,C4:E4,F4,TRUE) -> 0 | G11: =TREND(D11:F11,D4:F4,G4,TRUE) -> 0 | H11: =TREND(E11:G11,E4:G4,H4,TRUE) -> 0 | J11: 0 | K11: 0 | L11: 0 | M11: =TREND(J11:L11,J4:L4,M4,TRUE) -> 0 | N11: =TREND(K11:M11,K4:M4,N4,TRUE) -> 0 | O11: =TREND(L11:N11,L4:N4,O4,TRUE) -> 0
B12: Les prix de vos matières premières sur le marché varient-ils ? Si oui, à quelle fréquence ? | C12: 0 | D12: 0 | E12: 0 | F12: =TREND(C12:E12,C5:E5,F5,TRUE) -> 0 | G12: =TREND(D12:F12,D5:F5,G5,TRUE) -> 0 | H12: =TREND(E12:G12,E5:G5,H5,TRUE) -> 0 | J12: 0 | K12: 0 | L12: 0 | M12: =TREND(J12:L12,J5:L5,M5,TRUE) -> 0 | N12: =TREND(K12:M12,K5:M5,N5,TRUE) -> 0 | O12: =TREND(L12:N12,L5:N5,O5,TRUE) -> 0
B13: Les prix de vos produits sur le marché varient-ils ? Si oui, à quelle fréquence ? | C13: 0 | D13: 0 | E13: 0 | F13: =TREND(C13:E13,C6:E6,F6,TRUE) -> 0 | G13: =TREND(D13:F13,D6:F6,G6,TRUE) -> 0 | H13: =TREND(E13:G13,E6:G6,H6,TRUE) -> 0 | J13: 0 | K13: 0 | L13: 0 | M13: =TREND(J13:L13,J6:L6,M6,TRUE) -> 0 | N13: =TREND(K13:M13,K6:M6,N6,TRUE) -> 0 | O13: =TREND(L13:N13,L6:N6,O6,TRUE) -> 0
A14: Note sous-critère | C14: =(C11*0.5+C12*0.25+C13*0.25)*(10/6) -> 0 | D14: =(D11*0.5+D12*0.25+D13*0.25)*(10/6) -> 0 | E14: =(E11*0.5+E12*0.25+E13*0.25)*(10/6) -> 0 | F14: =(F11*0.5+F12*0.25+F13*0.25)*(10/6) -> 0 | G14: =(G11*0.5+G12*0.25+G13*0.25)*(10/6) -> 0 | H14: =(H11*0.5+H12*0.25+H13*0.25)*(10/6) -> 0 | J14: =(J11*0.5+J12*0.25+J13*0.25)*(10/6) -> 0 | K14: =(K11*0.5+K12*0.25+K13*0.25)*(10/6) -> 0 | L14: =(L11*0.5+L12*0.25+L13*0.25)*(10/6) -> 0 | M14: =(M11*0.5+M12*0.25+M13*0.25)*(10/6) -> 0 | N14: =(N11*0.5+N12*0.25+N13*0.25)*(10/6) -> 0 | O14: =(O11*0.5+O12*0.25+O13*0.25)*(10/6) -> 0
A15: Portefeuille produit | B15: En moyenne, quelle proportion de vos produits mis à la vente parvenez-vous à écouler par an? (entreprises industrielles et commerciales) En moyenne, quel est le niveau d’atteinte de vos objectifs de vente annuels ? (entreprises de services) PS : Les objectifs de vente peuvent être estimés par l’analyste à base de son bilan d’ouverture, sa capacité de production, etc. | C15: 0 | D15: 0 | E15: 0 | F15: =TREND(C15:E15,C4:E4,F4,) -> 0 | G15: =TREND(D15:F15,D4:F4,G4,) -> 0 | H15: =TREND(E15:G15,E4:G4,H4,) -> 0 | J15: 0 | K15: 0 | L15: 0 | M15: =TREND(J15:L15,J4:L4,M4,) -> 0 | N15: =TREND(K15:M15,K4:M4,N4,) -> 0 | O15: =TREND(L15:N15,L4:N4,O4,) -> 0
B16: Adaptez-vous vos produits ou services aux attentes de vos clients ? | C16: 0 | D16: 0 | E16: 0 | F16: =TREND(C16:E16,C5:E5,F5,) -> 0 | G16: =TREND(D16:F16,D5:F5,G5,) -> 0 | H16: =TREND(E16:G16,E5:G5,H5,) -> 0 | J16: 0 | K16: 0 | L16: 0 | M16: =TREND(J16:L16,J5:L5,M5,) -> 0 | N16: =TREND(K16:M16,K5:M5,N5,) -> 0 | O16: =TREND(L16:N16,L5:N5,O5,) -> 0
A17: Note sous-critère | C17: =(C15*0.5+C16*0.5)*(10/6) -> 0 | D17: =(D15*0.5+D16*0.5)*(10/6) -> 0 | E17: =(E15*0.5+E16*0.5)*(10/6) -> 0 | F17: =(F15*0.5+F16*0.5)*(10/6) -> 0 | G17: =(G15*0.5+G16*0.5)*(10/6) -> 0 | H17: =(H15*0.5+H16*0.5)*(10/6) -> 0 | J17: =(J15*0.5+J16*0.5)*(10/6) -> 0 | K17: =(K15*0.5+K16*0.5)*(10/6) -> 0 | L17: =(L15*0.5+L16*0.5)*(10/6) -> 0 | M17: =(M15*0.5+M16*0.5)*(10/6) -> 0 | N17: =(N15*0.5+N16*0.5)*(10/6) -> 0 | O17: =(O15*0.5+O16*0.5)*(10/6) -> 0
A18: Pression liée à la clientèle | B18: Quelle est la participation moyenne au chiffre d'affaire de vos principaux clients ? | C18: 0 | D18: 0 | E18: 0 | F18: =TREND(C18:E18,C4:E4,F4,) -> 0 | G18: =TREND(D18:F18,D4:F4,G4,) -> 0 | H18: =TREND(E18:G18,E4:G4,H4,) -> 0 | J18: 0 | K18: 0 | L18: 0 | M18: =TREND(J18:L18,J4:L4,M4,) -> 0 | N18: =TREND(K18:M18,K4:M4,N4,) -> 0 | O18: =TREND(L18:N18,L4:N4,O4,) -> 0
B19: Parmi eux, existe-t-il un qui représente plus de 10% de votre chiffre d'affaire ? Si oui, combien ? | C19: 0 | D19: 0 | E19: 0 | F19: =TREND(C19:E19,C5:E5,F5,) -> 0 | G19: =TREND(D19:F19,D5:F5,G5,) -> 0 | H19: =TREND(E19:G19,E5:G5,H5,) -> 0 | J19: 0 | K19: 0 | L19: 0 | M19: =TREND(J19:L19,J5:L5,M5,) -> 0 | N19: =TREND(K19:M19,K5:M5,N5,) -> 0 | O19: =TREND(L19:N19,L5:N5,O5,) -> 0
A20: Note sous-critère | C20: =(C18*0.6+C19*0.4)*(10/6) -> 0 | D20: =(D18*0.6+D19*0.4)*(10/6) -> 0 | E20: =(E18*0.6+E19*0.4)*(10/6) -> 0 | F20: =(F18*0.6+F19*0.4)*(10/6) -> 0 | G20: =(G18*0.6+G19*0.4)*(10/6) -> 0 | H20: =(H18*0.6+H19*0.4)*(10/6) -> 0 | J20: =(J18*0.6+J19*0.4)*(10/6) -> 0 | K20: =(K18*0.6+K19*0.4)*(10/6) -> 0 | L20: =(L18*0.6+L19*0.4)*(10/6) -> 0 | M20: =(M18*0.6+M19*0.4)*(10/6) -> 0 | N20: =(N18*0.6+N19*0.4)*(10/6) -> 0 | O20: =(O18*0.6+O19*0.4)*(10/6) -> 0
A21: Barrières à l'entrée | B21: Quel est le volume annuel des pertes financières associées aux contraintes administratives et fiscales dans l’exercice de votre activité ? | C21: 0 | D21: 0 | E21: 0 | F21: =TREND(C21:E21,C4:E4,F4,) -> 0 | G21: =TREND(D21:F21,D4:F4,G4,) -> 0 | H21: =TREND(E21:G21,E4:G4,H4,) -> 0 | J21: 0 | K21: 0 | L21: 0 | M21: =TREND(J21:L21,J4:L4,M4,) -> 0 | N21: =TREND(K21:M21,K4:M4,N4,) -> 0 | O21: =TREND(L21:N21,L4:N4,O4,) -> 0
B22: Quel est le volume annuel des pertes financières liées au déficit infrastructurel ? (défaut de voies de transport, défaut de moyens de transport adéquats, etc.) | C22: 0 | D22: 0 | E22: 0 | F22: =TREND(C22:E22,C5:E5,F5,) -> 0 | G22: =TREND(D22:F22,D5:F5,G5,) -> 0 | H22: =TREND(E22:G22,E5:G5,H5,) -> 0 | J22: 0 | K22: 0 | L22: 0 | M22: =TREND(J22:L22,J5:L5,M5,) -> 0 | N22: =TREND(K22:M22,K5:M5,N5,) -> 0 | O22: =TREND(L22:N22,L5:N5,O5,) -> 0
B23: Quel est le niveau de disponibilité des matières premières ? | C23: 0 | D23: 0 | E23: 0 | F23: =TREND(C23:E23,C6:E6,F6,) -> 0 | G23: =TREND(D23:F23,D6:F6,G6,) -> 0 | H23: =TREND(E23:G23,E6:G6,H6,) -> 0 | J23: 0 | K23: 0 | L23: 0 | M23: =TREND(J23:L23,J6:L6,M6,) -> 0 | N23: =TREND(K23:M23,K6:M6,N6,) -> 0 | O23: =TREND(L23:N23,L6:N6,O6,) -> 0
A24: Note sous-critère | C24: =(C21*0.3+C22*0.35+C23*0.35)*(10/6) -> 0 | D24: =(D21*0.3+D22*0.35+D23*0.35)*(10/6) -> 0 | E24: =(E21*0.3+E22*0.35+E23*0.35)*(10/6) -> 0 | F24: =(F21*0.3+F22*0.35+F23*0.35)*(10/6) -> 0 | G24: =(G21*0.3+G22*0.35+G23*0.35)*(10/6) -> 0 | H24: =(H21*0.3+H22*0.35+H23*0.35)*(10/6) -> 0 | J24: =(J21*0.3+J22*0.35+J23*0.35)*(10/6) -> 0 | K24: =(K21*0.3+K22*0.35+K23*0.35)*(10/6) -> 0 | L24: =(L21*0.3+L22*0.35+L23*0.35)*(10/6) -> 0 | M24: =(M21*0.3+M22*0.35+M23*0.35)*(10/6) -> 0 | N24: =(N21*0.3+N22*0.35+N23*0.35)*(10/6) -> 0 | O24: =(O21*0.3+O22*0.35+O23*0.35)*(10/6) -> 0
A25: Visibilité sur le secteur | B25: Pensez-vous qu’il existe des perspectives favorables en ce qui concerne votre secteur d’activité ? (réglementation, plans de développement, contraintes administratives et fiscales, subventionnements) Si oui, lesquelles ? Sinon, pourquoi ? | C25: 0 | D25: 0 | E25: 0 | F25: =TREND(C25:E25,C4:E4,F4:H4,) -> 0 | G25: =TREND(D25:F25,D4:F4,G4:J4,) -> 0 | H25: =TREND(E25:G25,E4:G4,H4:K4,) -> 0 | J25: 0 | K25: 0 | L25: 0 | M25: =TREND(J25:L25,J4:L4,M4,) -> 0 | N25: =TREND(K25:M25,K4:M4,N4,) -> 0 | O25: =TREND(L25:N25,L4:N4,O4,) -> 0
A26: Note sous-critère | C26: =(C25*1)*(10/6) -> 0 | D26: =(D25*1)*(10/6) -> 0 | E26: =(E25*1)*(10/6) -> 0 | F26: =(F25*1)*(10/6) -> 0 | G26: =(G25*1)*(10/6) -> 0 | H26: =(H25*1)*(10/6) -> 0 | J26: =(J25*1)*(10/6) -> 0 | K26: =(K25*1)*(10/6) -> 0 | L26: =(L25*1)*(10/6) -> 0 | M26: =(M25*1)*(10/6) -> 0 | N26: =(N25*1)*(10/6) -> 0 | O26: =(O25*1)*(10/6) -> 0
A27: Note CRITERE ACTIVITE | C27: =C8*0.15+C10*0.1+C14*0.1+C17*0.2+C20*0.2+C24*0.15+C26*0.1 -> 0 | D27: =D8*0.15+D10*0.1+D14*0.1+D17*0.2+D20*0.2+D24*0.15+D26*0.1 -> 0 | E27: =E8*0.15+E10*0.1+E14*0.1+E17*0.2+E20*0.2+E24*0.15+E26*0.1 -> 0 | F27: =F8*0.15+F10*0.1+F14*0.1+F17*0.2+F20*0.2+F24*0.15+F26*0.1 -> 0 | G27: =G8*0.15+G10*0.1+G14*0.1+G17*0.2+G20*0.2+G24*0.15+G26*0.1 -> 0 | H27: =H8*0.15+H10*0.1+H14*0.1+H17*0.2+H20*0.2+H24*0.15+H26*0.1 -> 0 | J27: =J8*0.15+J10*0.1+J14*0.1+J17*0.2+J20*0.2+J24*0.15+J26*0.1 -> 0 | K27: =K8*0.15+K10*0.1+K14*0.1+K17*0.2+K20*0.2+K24*0.15+K26*0.1 -> 0 | L27: =L8*0.15+L10*0.1+L14*0.1+L17*0.2+L20*0.2+L24*0.15+L26*0.1 -> 0 | M27: =M8*0.15+M10*0.1+M14*0.1+M17*0.2+M20*0.2+M24*0.15+M26*0.1 -> 0 | N27: =N8*0.15+N10*0.1+N14*0.1+N17*0.2+N20*0.2+N24*0.15+N26*0.1 -> 0 | O27: =O8*0.15+O10*0.1+O14*0.1+O17*0.2+O20*0.2+O24*0.15+O26*0.1 -> 0

Sheet Graphiques complémentaires
M25: Critère Activité - Secteur 1 | N25: Période 1 | O25: Période 2 | P25: Période 3
M26: Note moyenne | N26: =AVERAGE('Tendances et prévisions'!C27,'Tendances et prévisions'!J27) -> 0 | O26: =AVERAGE('Tendances et prévisions'!D27,'Tendances et prévisions'!K27) -> 0 | P26: =AVERAGE('Tendances et prévisions'!E27,'Tendances et prévisions'!L27) -> 0
M27: Note maximale | N27: =MAX('Tendances et prévisions'!C27,'Tendances et prévisions'!J27) -> 0 | O27: =MAX('Tendances et prévisions'!D27,'Tendances et prévisions'!K27) -> 0 | P27: =MAX('Tendances et prévisions'!E27,'Tendances et prévisions'!L27) -> 0
M28: Note minimale | N28: =MIN('Tendances et prévisions'!C27,'Tendances et prévisions'!J27) -> 0 | O28: =MIN('Tendances et prévisions'!D27,'Tendances et prévisions'!K27) -> 0 | P28: =MIN('Tendances et prévisions'!E27,'Tendances et prévisions'!L27) -> 0

Sheet tableaux annexes
C1: Valeur par sous-critère | D1: Note par sous-critère | E1: note pondérée | G1: Valeur par sous-critère | H1: Note par sous-critère | I1: Note pondérée | K1: Valeur par sous-critère | L1: Note par sous-critère | M1: Note pondérée | O1: Valeur par sous-critère | P1: Note par sous-critère | Q1: Note pondérée | S1: Valeur par sous-critère | T1: Note par sous-critère | U1: Note pondérée | W1: Valeur par sous-critère | X1: Note par sous-critère | Y1: Note pondérée | AA1: Valeur par sous-critère | AB1: Note par sous-critère | AC1: Note pondérée | AE1: Valeur par sous-critère | AF1: Note par sous-critère | AG1: Note pondérée | AI1: Valeur par sous-critère | AJ1: Note par sous-critère | AK1: Note pondérée | AM1: Valeur par sous-critère | AN1: Note par sous-critère | AO1: Note pondérée | AQ1: Valeur par sous-critère | AR1: Note par sous-critère | AS1: Note pondérée | AU1: Valeur par sous-critère | AV1: Note par sous-critère | AW1: Note pondérée | AY1: Valeur par sous-critère | AZ1: Note par sous-critère | BA1: Note pondérée | BC1: Valeur par sous-critère | BD1: Note par sous-critère | BE1: Note pondérée | BG1: Valeur par sous-critère | BH1: Note par sous-critère | BI1: Note pondérée | BK1: Valeur par sous-critère | BL1: Note par sous-critère | BM1: Note pondérée | BO1: Valeur par sous-critère | BP1: Note par sous-critère | BQ1: Note pondérée | BS1: Valeur par sous-critère | BT1: Note par sous-critère | BU1: Note pondérée | BW1: Valeur par sous-critère | BX1: Note par sous-critère | BY1: Note pondérée | CA1: Valeur par sous-critère | CB1: Note par sous-critère | CC1: Note pondérée
C2: Très significatif | D2: 1 | E2: 0.015 | G2: non | H2: 1 | I2: 0.01 | K2: très bonne A | L2: 1 | M2: 0.01 | O2: extremement bien positionné | P2: 1 | Q2: 0.02 | S2: très modérée | T2: 1 | U2: 0.02 | W2: très élevéés A | X2: 1 | Y2: 0.015 | AA2: très bonne A | AB2: 1 | AC2: 0.01 | AE2: excellente | AF2: 1 | AG2: 0.04 | AI2: excellente | AJ2: 1 | AK2: 0.02 | AM2: excellente | AN2: 1 | AO2: 0.02 | AQ2: importants,bien adaptés | AR2: 1 | AS2: 0.02 | AU2: excellente | AV2: 1 | AW2: 0.01 | AY2: très fiables dans l'ensemble | AZ2: 1 | BA2: 0.03 | BC2: excellente | BD2: 1 | BE2: 0.01 | BG2: Ne se pose pas du tout | BH2: 1 | BI2: 0.01 | BK2: très fiable | BL2: 1 | BM2: 0.03 | BO2: excellente | BP2: 1 | BQ2: 0.08 | BS2: très facile en permanence | BT2: 1 | BU2: 0.02 | BW2: oui, rapidement et importants | BX2: 1 | BY2: 0.07 | CA2: très cohérents | CB2: 1 | CC2: O,08
C3: Significatif | D3: 2 | E3: 0.03 | G3: non ou très peu | H3: 2 | I3: 0.02 | K3: très bonne B | L3: 2 | M3: 0.02 | O3: très bien positionné | P3: 2 | Q3: 0.02 | S3: modérée | T3: 2 | U3: 0.02 | W3: élevées | X3: 2 | AA3: très bonne B | AB3: 2 | AC3: 0.01 | AE3: très bonne | AF3: 2 | AG3: 0.04 | AI3: très bonne | AJ3: 2 | AK3: 0.02 | AM3: très bonne | AN3: 2 | AO3: 0.02 | AQ3: importants, adap^tés | AR3: 2 | AS3: 0.02 | AU3: très bonne | AV3: 2 | AW3: 0.02 | AY3: plutôt fiables A | AZ3: 2 | BA3: 0.02 | BC3: très bonne | BD3: 2 | BG3: Ne se pose pas | BH3: 2 | BI3: 0.02 | BK3: fiable | BL3: 2 | BO3: très bonne | BP3: 2 | BS3: facile en conjoncture normale A | BT3: 2 | BW3: oui, assez rapidement et assez importants | BX3: 2 | CA3: cohérents | CB3: 2
C4: Bon | D4: 3 | E4: 0.045 | G4: peu | H4: 3 | I4: 0.03 | K4: bonne | L4: 3 | M4: 0.03 | O4: plutot bien positionné | P4: 3 | Q4: 0.06 | S4: plutôt faible | T4: 3 | U4: 0.06 | W4: élevées | X4: 3 | Y4: 0.045 | AA4: bonne A | AB4: 3 | AC4: 0.03 | AE4: bonne | AF4: 3 | AG4: 0.12 | AI4: bonne | AJ4: 3 | AK4: 0.06 | AM4: bonne | AN4: 3 | AO4: 0.06 | AQ4: assez importants | AR4: 3 | AS4: 0.06 | AU4: bonne | AV4: 3 | AW4: 0.03 | AY4: plutôt fiables B | AZ4: 3 | BA4: 0.09 | BC4: bonne | BD4: 3 | BE4: 0.03 | BG4: Garantie par le cadre juridique et fonctionnel | BH4: 3 | BI4: 0.03 | BK4: plutôt fiable A | BL4: 3 | BM4: O,09 | BO4: bonne | BP4: 3 | BQ4: 0.24 | BS4: facile en conjoncture normale B | BT4: 3 | BU4: 0.06 | BW4: oui, sans delai A | BX4: 3 | BY4: 0.21 | CA4: plutôt cohérents A | CB4: 3 | CC4: O,24
C5: Plutôt Bon | D5: 4 | E5: 0.06 | G5: légèrement | H5: 4 | I5: 0.04 | K5: moyenne | L5: 4 | M5: 0.04 | O5: assez bien positionné | P5: 4 | Q5: 0.08 | S5: plutot sensible | T5: 4 | U5: 0.08 | W5: assez élevées | X5: 4 | Y5: 0.06 | AA5: bonne B | AB5: 4 | AC5: 0.04 | AE5: assez bonne | AF5: 4 | AG5: 0.16 | AI5: assez bonne | AJ5: 4 | AK5: 0.08 | AM5: assez bonne | AN5: 4 | AO5: 0.08 | AQ5: suffisants | AR5: 4 | AS5: 0.08 | AU5: assez bonne | AV5: 4 | AW5: 0.04 | AY5: fiables | AZ5: 4 | BA5: 0.12 | BC5: assez bonne | BD5: 4 | BE5: 0.04 | BG5: Garantie par le cadre juridique | BH5: 4 | BI5: 0.04 | BK5: plutôt fiable B | BL5: 4 | BM5: 0.12 | BO5: assez bonne | BP5: 4 | BQ5: 0.32 | BS5: limité en conjocture normale A | BT5: 4 | BU5: 0.08 | BW5: oui, sans delai B | BX5: 4 | BY5: 0.28 | CA5: plutôt cohérents B | CB5: 4 | CC5: 0.32
C6: Moyen | D6: 5 | E6: 0.075 | G6: modérement B | H6: 5 | I6: 0.05 | K6: faible | L6: 5 | M6: 0.05 | O6: moyennement positionné A | P6: 5 | Q6: 0.1 | S6: assez sensible | T6: 5 | U6: 0.1 | W6: plutôt faibles | X6: 5 | Y6: 0.075 | AA6: moyenne à moyen terme | AB6: 5 | AC6: 0.05 | AE6: moyenne | AF6: 5 | AG6: 0.2 | AI6: moyenne | AJ6: 5 | AK6: 0.1 | AM6: moyenne | AN6: 5 | AO6: 0.1 | AQ6: plutôt faibles | AR6: 5 | AS6: 0.1 | AU6: moyenne | AV6: 5 | AW6: 0.05 | AY6: moyennement fiables | AZ6: 5 | BA6: 0.15 | BC6: moyenne | BD6: 5 | BE6: 0.05 | BG6: Assurée depuis un certain temps (Moyen) | BH6: 5 | BI6: 0.05 | BK6: moyennement fiable | BL6: 5 | BM6: 0.15 | BO6: moyenne | BP6: 5 | BQ6: 0.4 | BS6: limité en conjocture normale B | BT6: 5 | BU6: 0.1 | BW6: Surface financière limitée | BX6: 5 | BY6: 0.28 | CA6: moyennement cohérents | CB6: 5 | CC6: 0.4
C7: Plutôt Moyen | D7: 6 | E7: 0.09 | G7: modérement A | H7: 6 | I7: 0.06 | K7: plutôt en stagnation | L7: 6 | M7: 0.06 | O7: moyennement positionné B | P7: 6 | Q7: 0.12 | S7: sensible | T7: 6 | U7: 0.12 | W7: faibles | X7: 6 | Y7: 0.09 | AA7: limitée à moyen terme | AB7: 6 | AC7: 0.06 | AE7: plutôt moyenne | AF7: 6 | AG7: 0.24 | AI7: plutôt moyenne | AJ7: 6 | AK7: 0.12 | AM7: plutôt moyenne | AN7: 6 | AO7: 0.12 | AQ7: faibles | AR7: 6 | AS7: 0.12 | AU7: plutôt faible | AV7: 6 | AW7: 0.06 | AY7: pas toufours fiables | AZ7: 6 | BA7: 0.18 | BC7: limitée | BD7: 6 | BE7: 0.06 | BG7: Assurée depuis quelque temps (Court) | BH7: 6 | BI7: 0.06 | BK7: pas toujours fiable | BL7: 6 | BM7: 0.18 | BO7: plutôt moyenne | BP7: 6 | BQ7: 0.48 | BS7: incertain mais envisageable | BT7: 6 | BU7: 0.12 | BW7: Surface financière faible | BX7: 6 | BY7: 0.28 | CA7: pas toujours cohérents | CB7: 6 | CC7: 0.48
C8: Faible | D8: 7 | E8: 0.105 | G8: fortement B | H8: 7 | I8: 0.07 | K8: plutôt en baisse | L8: 7 | M8: 0.07 | O8: plutôt mal positionné et/ou étroit | P8: 7 | Q8: 0.14 | S8: assez forte | T8: 7 | U8: 0.14 | W8: très faibles A | X8: 7 | Y8: 0.105 | AA8: plutot faible | AB8: 7 | AC8: 0.07 | AE8: mauvaise | AF8: 7 | AG8: 0.28 | AI8: mauvaise | AJ8: 7 | AK8: 0.14 | AM8: mauvaise | AN8: 7 | AO8: 0.14 | AQ8: insuffisants A | AR8: 7 | AS8: 0.14 | AU8: faible | AV8: 7 | AW8: 0.07 | AY8: peu fiables | AZ8: 7 | BA8: 0.21 | BC8: plutôt faible | BD8: 7 | BE8: 0.07 | BG8: se pose à moyen terme, relève non prévue | BH8: 7 | BI8: 0.07 | BK8: peu fiable | BL8: 7 | BM8: 0.21 | BO8: mauvaise | BP8: 7 | BQ8: 0.56 | BS8: difficile mais possible | BT8: 7 | BU8: 0.14 | BW8: Surface financière très faible | BX8: 7 | BY8: 0.28 | CA8: peu cohérents | CB8: 7 | CC8: 0.56
C9: Limité | D9: 8 | E9: 0.12 | G9: fortement A | H9: 8 | I9: 0.08 | K9: en baisse sensible | L9: 8 | M9: 0.08 | O9: mal positionné et/ou très étroit | P9: 8 | Q9: 0.16 | S9: forte | T9: 8 | U9: 0.16 | W9: très faibles B | X9: 8 | Y9: 0.12 | AA9: faible | AB9: 8 | AC9: 0.08 | AE9: limitée | AF9: 8 | AG9: 0.32 | AI9: limitée | AJ9: 8 | AK9: 0.16 | AM9: limitée | AN9: 8 | AO9: 0.16 | AQ9: insuffisants B | AR9: 8 | AS9: 0.16 | AU9: limité | AV9: 8 | AW9: 0.08 | AY9: peu ou pas fiables ou non communiquées | AZ9: 8 | BA9: 0.24 | BC9: faible | BD9: 8 | BE9: 0.08 | BG9: se pose à court terme,relève non assurée | BH9: 8 | BI9: 0.08 | BK9: peu ou pas fiable | BL9: 8 | BM9: 0.24 | BO9: limitée | BP9: 8 | BQ9: 0.64 | BS9: très peu probable | BT9: 8 | BU9: 0.16 | BW9: Patrimoine insignifiant | BX9: 8 | BY9: 0.28 | CA9: peu ou pas cohérents | CB9: 8 | CC9: 0.64
C10: Mauvais | D10: 9 | E10: 0.135 | G10: très fortement B | H10: 9 | I10: 0.09 | K10: en forte baisse | L10: 9 | M10: 0.09 | O10: renouvellement non assuré | P10: 9 | Q10: 0.18 | S10: très forte | T10: 9 | U10: 0.18 | W10: inexistentes A | X10: 9 | Y10: 0.135 | AA10: très faible | AB10: 9 | AC10: 0.09 | AE10: très mauvaise A | AF10: 9 | AG10: 0.36 | AI10: très mauvaise A | AJ10: 9 | AK10: 0.18 | AM10: très mauvaise A | AN10: 9 | AO10: 0.18 | AQ10: très insuffisants A | AR10: 9 | AS10: 0.18 | AU10: très limitée | AV10: 9 | AW10: 0.09 | AY10: pas fiables A | AZ10: 9 | BA10: 0.27 | BC10: mauvaise | BD10: 9 | BE10: 0.09 | BG10: problème aigue de succession | BH10: 9 | BI10: 0.09 | BK10: pas fiable A | BL10: 9 | BM10: 0.27 | BO10: très mauvaise A | BP10: 9 | BQ10: 0.72 | BS10: non pas d'appui A | BT10: 9 | BU10: 0.18 | BW10: Non, pas patrimoine personnel | BX10: 9 | BY10: 0.28 | CA10: pas cohérents A | CB10: 9 | CC10: 0.72
C11: Très Mauvais | D11: 10 | E11: 0.15 | G11: très fortement A | H11: 10 | I11: 0.1 | K11: secteur en difficulté ou en déclin | L11: 10 | M11: 0.1 | O11: obsolescence marquée | P11: 10 | Q11: 0.2 | S11: extremement forte | T11: 10 | U11: 0.2 | W11: inexistentes B | X11: 10 | Y11: 0.15 | AA11: extrement faible | AB11: 10 | AC11: 0.1 | AE11: très mauvaise B | AF11: 10 | AG11: 0.4 | AI11: très mauvaise B | AJ11: 10 | AK11: 0.2 | AM11: très mauvaise B | AN11: 10 | AO11: 0.2 | AQ11: très insuffisants B | AR11: 10 | AS11: 0.2 | AU11: inexistente | AV11: 10 | AW11: 0.1 | AY11: pas fiables B | AZ11: 10 | BA11: 0.3 | BC11: très mauvaise | BD11: 10 | BE11: 0.1 | BG11: gestion par administrateur | BH11: 10 | BI11: 0.1 | BK11: pas fiable B | BL11: 10 | BM11: 0.3 | BO11: très mauvaise B | BP11: 10 | BQ11: 0.8 | BS11: non pas d'appui B | BT11: 10 | BU11: 0.2 | BW11: Non, pas de patrimoine du tout | BX11: 10 | BY11: 0.28 | CA11: pas cohérents B | CB11: 10 | CC11: 0.8
BW13: oui, sans delai B
C19: Valeur par sous-critère | D19: Note par sous-critère | E19: Note pondérée
C20: très bonne A | D20: 1 | E20: 0.01
C21: très bonne B | D21: 2 | E21: 0.02
C22: bonne | D22: 3 | E22: 0.03
C23: moyenne | D23: 4 | E23: 0.04
C24: faible | D24: 5 | E24: 0.05
C25: plutôt en stagnation | D25: 6 | E25: 0.06
C26: plutôt en baisse | D26: 7 | E26: 0.07
C27: en baisse sensible | D27: 8 | E27: 0.08
C28: en forte baisse | D28: 9 | E28: 0.09
C29: secteur en difficulté ou en déclin | D29: 10 | E29: 0.01
